[{"uid": "604757897", "content": "跟男生绝缘一段时间就正常了"}, {"uid": "475184166", "content": "这是舔狗和备胎的作用"}, {"uid": "432167463", "content": "用手然后洗掉，QwQ"}, {"uid": "474193178", "content": "富婆应该直接用钱"}, {"uid": "189627719", "content": "骗舰的屑猫"}, {"uid": "189627719", "content": "不对劲"}, {"uid": "189627719", "content": "老大哥？"}, {"uid": "189627719", "content": "我从未见过如此奇怪的要求"}, {"uid": "189627719", "content": "好的取关了"}, {"uid": "189627719", "content": "用来欺负妮妮的"}, {"uid": "343299596", "content": "哥哥不是让妹妹跑腿的吗？？？"}, {"uid": "443529239", "content": "我只会心疼哥哥"}, {"uid": "9271508", "content": "妮妮只会心疼giegie~"}, {"uid": "496316623", "content": "因为粉丝多了飘了"}, {"uid": "504564570", "content": "天动万象"}, {"uid": "37815622", "content": "（知识增加）好啊好啊"}, {"uid": "216178994", "content": "所以哥哥=爸爸（雾）"}, {"uid": "216178994", "content": "所以哥哥=爸爸"}, {"uid": "216178994", "content": "所以哥哥="}, {"uid": "416190396", "content": "好可爱的钉宫妮妮"}, {"uid": "12754387", "content": "主要怕被角刺死"}, {"uid": "12754387", "content": "图 穷 匕 见"}, {"uid": "12754387", "content": "纯路人，这就是茶艺大师吗"}, {"uid": "326128545", "content": "四川人震怒（doge）"}, {"uid": "326294813", "content": "首尾呼应"}, {"uid": "326294813", "content": "绿茶"}, {"uid": "445512403", "content": "热乎"}, {"uid": "13382909", "content": "草"}, {"uid": "14016742", "content": "草"}, {"uid": "19724079", "content": "好的，这就取关"}, {"uid": "520874651", "content": "这个帝君BGM认真的吗（）"}, {"uid": "46252062", "content": "草。什么屑猫"}, {"uid": "471414414", "content": "措不及防"}, {"uid": "387375861", "content": "有24小时营业的超市能买的到吧"}, {"uid": "43483033", "content": "好的。立马关注"}, {"uid": "441353269", "content": "哈哈哈哈"}, {"uid": "60501474", "content": "我家有"}, {"uid": "342776407", "content": "原形毕露！"}, {"uid": "436213202", "content": "召唤拳头呈攻击表示"}, {"uid": "4218620", "content": "泪目"}, {"uid": "20568929", "content": "草（一种植物）"}, {"uid": "22587065", "content": "尼酱我也不是不行"}, {"uid": "262104075", "content": "出门买啊"}, {"uid": "28276707", "content": "屑猫语录"}, {"uid": "16069967", "content": "当然不能"}, {"uid": "189627719", "content": "你说这个我可就不困了"}, {"uid": "189627719", "content": "开屏雷击"}, {"uid": "37815622", "content": "草，钟离的bgm"}, {"uid": "414192041", "content": "俗称姨妈巾"}, {"uid": "343299596", "content": "本想点个取关，没想到还没关注。。。"}, {"uid": "37815622", "content": "真的吗？？那我要打妮妮的屁股（女少口阿）"}, {"uid": "216178994", "content": "生活不易"}, {"uid": "28675688", "content": "哈哈哈"}, {"uid": "471414414", "content": "好啊，没问题啊(杰哥"}, {"uid": "471654961", "content": "太屑了！！"}, {"uid": "319204127", "content": "砂纸了解一下？？？"}, {"uid": "14016742", "content": "好呀好呀"}, {"uid": "19724079", "content": "没见过这么奇怪的要求（一拳"}, {"uid": "57794177", "content": "五分钟热乎"}, {"uid": "282642875", "content": "？？？？"}, {"uid": "10610167", "content": "？？？"}, {"uid": "236599582", "content": "懂了，这就取关"}, {"uid": "93806810", "content": "上勾拳！！！"}, {"uid": "596029514", "content": "懂了，这就取关。 啊？我没关注？那没事了"}, {"uid": "57578913", "content": "都怪bt"}, {"uid": "401858702", "content": "迷迭迷迭帕里桑~"}, {"uid": "434205589", "content": "好快的cece"}, {"uid": "702710120", "content": "鬼！"}, {"uid": "5632434", "content": "草"}, {"uid": "38724068", "content": "草"}, {"uid": "237433070", "content": "砂纸呢？"}, {"uid": "239139", "content": "草"}, {"uid": "16069967", "content": "就是用来玩妮妮的"}, {"uid": "363228711", "content": "六六六"}, {"uid": "34988307", "content": "？？"}, {"uid": "266986370", "content": "？？？"}, {"uid": "266986370", "content": "好的"}, {"uid": "14850581", "content": "？"}, {"uid": "372337256", "content": "热乎"}, {"uid": "28675688", "content": "Xxbt"}, {"uid": "9212109", "content": "？"}, {"uid": "100564147", "content": "12分钟"}, {"uid": "436213202", "content": "草"}, {"uid": "436213202", "content": "草"}, {"uid": "319204127", "content": "明白了，取关"}, {"uid": "240714118", "content": "？"}, {"uid": "8123513", "content": "?"}, {"uid": "5383303", "content": "？"}, {"uid": "441390038", "content": "不可以，滚"}, {"uid": "10440446", "content": "無駄無駄無駄無駄無駄無駄無駄無駄無駄無駄"}, {"uid": "355982612", "content": "有妹纸"}]