[{"uid": "86954029", "content": "你和雪菜亲过多少次了啊！"}, {"uid": "86954029", "content": "为什么你会这么熟练啊！"}, {"uid": "86954029", "content": "草 ic的op 谢谢 胃已经开始疼了"}, {"uid": "3350661", "content": "草"}, {"uid": "12980663", "content": "一首届不到的恋送给在座的各位"}, {"uid": "3654358", "content": "情人节快乐？"}, {"uid": "1477209", "content": "这歌也算是情人节定番了吧"}, {"uid": "4690860", "content": "这句唱的不太对 哈哈"}, {"uid": "1853150", "content": "胃啊啊啊啊"}, {"uid": "8464461", "content": "梦里不觉秋已深，余情岂是为他人"}, {"uid": "30514029", "content": "卧槽，好家伙"}, {"uid": "37944363", "content": "胃疼了"}, {"uid": "7454324", "content": "好家伙"}, {"uid": "7298450", "content": "我的胃开始疼了"}, {"uid": "30327137", "content": "刚吃完饭的我。。"}, {"uid": "444450", "content": "草"}, {"uid": "544972", "content": "啊这.."}, {"uid": "4415679", "content": "caO"}, {"uid": "6370780", "content": "草"}]