[{"uid": "94741753", "content": "巴蒂才是女儿←"}, {"uid": "372743634", "content": "这里可以刷级 brad一个滑铲（误）一个头滑搞定一切"}, {"uid": "372743634", "content": "一通连招"}, {"uid": "372743634", "content": "不要停下来啊"}, {"uid": "372743634", "content": "白衣小女孩是lisa"}, {"uid": "372743634", "content": "拿到卡车后我看你怎么说"}, {"uid": "372743634", "content": "terry能带了吗"}, {"uid": "372743634", "content": "完蛋"}, {"uid": "372743634", "content": "爆炸头"}, {"uid": "372743634", "content": "头发跌倒了"}, {"uid": "372743634", "content": "还记得之前那个人说头发易燃吗？"}, {"uid": "372743634", "content": "屁，terry刷级上去了nern鬼故事讲得好打得过"}, {"uid": "372743634", "content": "前面只是玩个梗，主角后期一个头滑搞定一切"}, {"uid": "372743634", "content": "最弱恐成主角"}, {"uid": "372743634", "content": "要terry"}, {"uid": "372743634", "content": "terry刷级刷上去好打，注意nern鬼故事控一下"}, {"uid": "372743634", "content": "不带terry的后果"}, {"uid": "372743634", "content": "不用燃烧瓶，terry刷一下级就过去了 还有就是一定多用点控制技（nern鬼故事）"}, {"uid": "372743634", "content": "terry一个巴西热舞把你游戏打炸了"}, {"uid": "372743634", "content": "结局带terry你会很感动的，相信我"}, {"uid": "372743634", "content": "别换啊，非得换？我通关队就这terry加nern加酒鬼"}, {"uid": "372743634", "content": "别换"}, {"uid": "372743634", "content": "terry，nern，酒鬼，我认为的最强队伍"}, {"uid": "37901398", "content": "川普"}, {"uid": "36043921", "content": "中毒了所以攻击力低啦"}, {"uid": "210140699", "content": "晚安玛卡巴卡"}, {"uid": "31391270", "content": "后知后觉"}, {"uid": "31391270", "content": "欧皇鹅"}, {"uid": "17647792", "content": "大E了大E了"}, {"uid": "8067212", "content": "哈哈哈哈哈哈哈哈哈哈哈哈哈哈"}, {"uid": "8067212", "content": "哈哈哈哈哈哈哈哈哈哈哈哈哈"}, {"uid": "8067212", "content": "hhhhhhhh"}, {"uid": "8067212", "content": "hhhhhhhhhh翻车"}, {"uid": "8067212", "content": "哈哈哈哈哈哈哈哈哈哈哈"}, {"uid": "8067212", "content": "鬼故事 永远的神"}, {"uid": "8067212", "content": "哈哈哈哈哈哈哈哈哈哈哈"}, {"uid": "8067212", "content": "hhhhhhhhhh"}, {"uid": "8067212", "content": "hhhhhhhhh"}, {"uid": "8067212", "content": "23333333我还以为我电脑炸了"}, {"uid": "386186356", "content": "这个人是把风的 所以后面就被抢了是吗？"}, {"uid": "386186356", "content": "右边是个碧池"}, {"uid": "386186356", "content": "等等 我好像看懂了。。被绿了"}, {"uid": "386186356", "content": "换brad的认真的？"}, {"uid": "152297614", "content": "1"}, {"uid": "152297614", "content": "001"}, {"uid": "152297614", "content": "123"}, {"uid": "152297614", "content": "21"}, {"uid": "152297614", "content": "213"}, {"uid": "152297614", "content": "123"}, {"uid": "15113298", "content": "这个人是续作boss"}, {"uid": "8287989", "content": "一口一个小朋友"}, {"uid": "8287989", "content": "house"}, {"uid": "37870050", "content": "？？？？"}, {"uid": "37870050", "content": "不要停下来啊啊啊啊啊！！"}, {"uid": "108538612", "content": "这里可以看到yado，joy的创造者，buddy的父亲"}, {"uid": "205081342", "content": "给头发讲鬼故事"}, {"uid": "470045746", "content": "这里我用brad头滑赢得，sdds全晕"}, {"uid": "370262561", "content": "Terry配合酒鬼一招2w都给你打出来"}, {"uid": "370262561", "content": "就用terry吧，后期伤害爆炸"}, {"uid": "9215914", "content": "为了窒息快感吧"}, {"uid": "171423077", "content": "令人窒息的操作"}, {"uid": "8561678", "content": "不是这"}, {"uid": "2529937", "content": "毛多弱火"}, {"uid": "3437219", "content": "awwd错了那么多次为什么还那么执着？？"}, {"uid": "87370358", "content": "直接往右下去不行吗。。"}, {"uid": "372743634", "content": "而且结局带泰瑞（算了我别剧透了）"}, {"uid": "141744420", "content": "然而terry是最强后期"}, {"uid": "281626708", "content": "他为什么活着？"}, {"uid": "281626708", "content": "完美给自己打崩了"}, {"uid": "281626708", "content": "我心态崩了啊"}, {"uid": "281626708", "content": "需要一张子来写下来"}, {"uid": "281626708", "content": "感觉不用回血反正都是一下秒"}, {"uid": "281626708", "content": "瓶子。。。。"}, {"uid": "44712317", "content": "？！"}, {"uid": "44712317", "content": "开始学着存别的档了吗哈哈哈"}, {"uid": "44712317", "content": "弹演好"}, {"uid": "44712317", "content": "哈哈哈哈哈？？"}, {"uid": "44712317", "content": "噗，不要睡在野外"}, {"uid": "6457836", "content": "李是猪吧"}, {"uid": "6457836", "content": "2秒记忆力2333"}, {"uid": "2835293", "content": "我有次睡醒队友跑了"}, {"uid": "370209504", "content": "Terry是真的没用"}, {"uid": "12613866", "content": "读档火瓶"}, {"uid": "12613866", "content": "哈"}, {"uid": "12613866", "content": "买拖拉机"}, {"uid": "11617767", "content": "这个洞进去再出来有超强敌人，老鹅现在没柴油瓶估计gg了"}, {"uid": "11617767", "content": "小黄书-100"}, {"uid": "11617767", "content": "老e真他喵欧"}, {"uid": "11617767", "content": "可是头发打人非常痛"}, {"uid": "382129102", "content": "记住这个人"}, {"uid": "19864512", "content": "飞起来噜"}, {"uid": "3057968", "content": "好难打的_(:з」∠)_"}, {"uid": "3057968", "content": "nern后期能补血"}, {"uid": "13503870", "content": "背在背上了啊"}, {"uid": "13503870", "content": "火男还会被点燃呢"}, {"uid": "13503870", "content": "你还可以玩更久"}, {"uid": "38990854", "content": "一gay我里giaogiao！"}, {"uid": "358260", "content": "应该是“整理发型”吧"}, {"uid": "13426613", "content": "杂志就是小黄书，这个翻译翻的不好而已，都是mags"}, {"uid": "3133474", "content": "搞不懂为啥一定要换，是有什么不满还是那个很强"}, {"uid": "3133474", "content": "把主角换了吧"}, {"uid": "26163676", "content": "勇士之路拿到小单车"}, {"uid": "26163676", "content": "唉"}, {"uid": "26163676", "content": "Terry史上最强的队友，没有之一"}, {"uid": "957228", "content": "这里能赢的"}, {"uid": "957228", "content": "23333333"}, {"uid": "382129102", "content": "人工弹幕"}, {"uid": "4474341", "content": "两个嘴炮两个输出 还可以"}, {"uid": "1345164", "content": "6666666"}, {"uid": "188155999", "content": "233"}, {"uid": "1721411", "content": "弹幕演员够了！"}, {"uid": "343310197", "content": "55666"}, {"uid": "343310197", "content": "心存款吧，小笨蛋。"}, {"uid": "343310197", "content": "，吓死了"}, {"uid": "3469337", "content": "靠声音来记忆就容易忘，还得眼睛看才行"}, {"uid": "3469337", "content": "坚持杀戒，一但破了就是尸山血海233"}, {"uid": "101581360", "content": "那么好听继续吹啊"}, {"uid": "101581360", "content": "所以你之前浪费一个？"}, {"uid": "101581360", "content": "嗜血成性的鹅"}, {"uid": "101581360", "content": "不换不就好啦？"}, {"uid": "101581360", "content": "不换不行？"}, {"uid": "101581360", "content": "废物个屁"}, {"uid": "101581360", "content": "泰瑞留着怎么了？笑点支撑啊"}, {"uid": "101581360", "content": "气人？"}, {"uid": "101581360", "content": "我记13个都没问题，老鹅四个都够呛？"}, {"uid": "101581360", "content": "按出来也要废点数"}, {"uid": "101581360", "content": "空气开始变得焦灼"}, {"uid": "197834675", "content": "我没开弹幕？"}, {"uid": "2554132", "content": "团..."}, {"uid": "198494663", "content": "音乐带感"}, {"uid": "318822490", "content": "头发是中指"}, {"uid": "333350878", "content": "。。。。。。"}, {"uid": "374005", "content": "感觉是流言"}, {"uid": "374005", "content": "666"}, {"uid": "17302", "content": "好了，嚷嚷的人能闭嘴了吗"}, {"uid": "17302", "content": "梗而已"}, {"uid": "17302", "content": "左边下"}, {"uid": "51413759", "content": "主角不能换"}, {"uid": "51413759", "content": "为什么不让他跟自己谈论力量"}, {"uid": "192292778", "content": "还不如Terry"}, {"uid": "97538328", "content": "这女孩长的真的丑，是女的吗？这帮人有可能是眼瞎"}, {"uid": "97538328", "content": "愚蠢的鹅类"}, {"uid": "7906825", "content": "他没有女儿"}, {"uid": "7906825", "content": "对着头发讲鬼故事还行"}, {"uid": "7906825", "content": "之后打杀马特的提示"}, {"uid": "7906825", "content": "持续回血状态"}, {"uid": "1488515", "content": "烧他头发"}, {"uid": "773113", "content": "恭喜恭喜"}, {"uid": "773113", "content": "呵呵"}, {"uid": "8458080", "content": "心疼一下这位小哥..."}, {"uid": "773113", "content": "李是猪吧"}, {"uid": "773113", "content": "钱都可以刷了，留着生孩子吗？"}, {"uid": "8458080", "content": "同喜欢Terry"}, {"uid": "8458080", "content": "就不要把terry换掉啦w"}, {"uid": "773113", "content": "...绝了，你一定是王老菊二代"}, {"uid": "2197879", "content": "注意这里是无效"}, {"uid": "245775443", "content": "我也觉得挺好，可惜没手机版"}, {"uid": "245775443", "content": "没事，不心疼，后面有人抢"}, {"uid": "245775443", "content": "以其人之道，还治其人之身"}, {"uid": "935670", "content": "可以啊"}, {"uid": "935670", "content": "死透了233"}, {"uid": "935670", "content": "蛇跌倒了！"}, {"uid": "34490862", "content": "然鹅并没有发生什么事233"}, {"uid": "34490862", "content": "Joyful？？！！啊？？！！！"}, {"uid": "34490862", "content": "Rando 不 是 Brad 你 的 徒 弟 吗 ！！！"}, {"uid": "34490862", "content": "另一位小伙伴你好吖"}, {"uid": "34490862", "content": "说要什么自行车的智商消失不见了吗"}, {"uid": "35096320", "content": "嗑什么药  主角之前早就被强嗑了药  现在状态还有磕药效果"}, {"uid": "6083076", "content": "233333333"}, {"uid": "14183574", "content": "自行车啊大哥1"}, {"uid": "9035174", "content": "又忘了233333"}, {"uid": "31749648", "content": "读档然后疯狂买东西呗"}, {"uid": "35208334", "content": "因为你懂我的心~~~"}, {"uid": "43254220", "content": "卧槽这个家。。。开头那个？"}, {"uid": "43254220", "content": "虽然Terry很弱，但我最喜欢的还是Terry啊，超蠢假向导"}, {"uid": "43254220", "content": "在这qwq"}, {"uid": "42542987", "content": "是男主的小伙伴"}, {"uid": "42542987", "content": "想想之前他跳的那么high，好压抑啊"}, {"uid": "42542987", "content": "好压抑啊"}, {"uid": "42542987", "content": "之前的都有枪啊"}, {"uid": "42542987", "content": "就是这个吹号的人"}, {"uid": "42542987", "content": "玩这个游戏的第三部你会发现这个人是最关键的剧情人物"}, {"uid": "177287287", "content": "2000+了，，，，，"}, {"uid": "177287287", "content": "杂志，，，，，，"}, {"uid": "177287287", "content": "23333，，，，，"}, {"uid": "177287287", "content": "对对，是，，，，，"}, {"uid": "177287287", "content": "不是有个燃烧瓶，，，，，怼"}, {"uid": "177287287", "content": "场景是，，，，，"}, {"uid": "32171563", "content": "terry25级有个很强的技能配合酒鬼"}, {"uid": "32171563", "content": "一样的啊"}, {"uid": "32171563", "content": "不是那个工厂啊"}, {"uid": "2249271", "content": "lisa！"}, {"uid": "2249271", "content": "抠"}, {"uid": "2249271", "content": "nern有用"}, {"uid": "2249271", "content": "是妹妹"}, {"uid": "42542987", "content": "因为司机眼泪多啊"}, {"uid": "42542987", "content": "火瓶不要钱的啊"}, {"uid": "35421634", "content": "葬爱家族"}, {"uid": "358260", "content": "bgm是上面那人吹出来的"}, {"uid": "40453929", "content": "。"}, {"uid": "40453929", "content": "nern只能加sp和tp"}, {"uid": "40453929", "content": "Terry好像也有加sp的技能"}, {"uid": "12321577", "content": "半雷"}, {"uid": "9868600", "content": "这是回忆"}, {"uid": "9868600", "content": "嗑药太多虚幻了"}, {"uid": "9868600", "content": "瞎子哦"}, {"uid": "9868600", "content": "草吓死我了"}, {"uid": "9868600", "content": "直接跳下去啊"}, {"uid": "9868600", "content": "失败"}, {"uid": "9868600", "content": "听完啊"}, {"uid": "15119805", "content": "最后都变光头？"}, {"uid": "7966384", "content": "233333333"}, {"uid": "641753", "content": "秒怂"}, {"uid": "60765208", "content": "这个秋千。这个篮球架。。"}, {"uid": "4288098", "content": "哈哈哈哈哈哈哈"}, {"uid": "4288098", "content": "蛋碎"}, {"uid": "2673184", "content": "让你一直存一个档 哈哈哈哈"}, {"uid": "2673184", "content": "重打吧，亏死了"}, {"uid": "2673184", "content": "？？？怕不是故意的"}, {"uid": "2673184", "content": "金鱼的记忆"}, {"uid": "23667214", "content": "23333"}, {"uid": "8096502", "content": "带"}, {"uid": "8096502", "content": "嗨"}, {"uid": "8096502", "content": "鹅操作很好的"}, {"uid": "8096502", "content": "你上次打他的时候他还说不要鞭尸"}, {"uid": "8096502", "content": "哈哈哈哈哈"}, {"uid": "8096502", "content": "喜欢李啊"}, {"uid": "8096502", "content": "哈哈哈蠢鹅"}, {"uid": "8096502", "content": "心疼鹅"}, {"uid": "8109255", "content": "chicken manman"}, {"uid": "8109255", "content": "365里路"}, {"uid": "65154690", "content": "team kill"}, {"uid": "65154690", "content": "其实terry后期贼强"}, {"uid": "65154690", "content": "苟"}, {"uid": "65154690", "content": "其实那个人是拿弓的"}, {"uid": "398318", "content": "完了 真当他看太阳啊。。"}, {"uid": "30471101", "content": "读档不就好了"}, {"uid": "12041748", "content": "然而你之前来这里的时候已经杀了= ="}, {"uid": "12041748", "content": "野外会有各种意外"}, {"uid": "12041748", "content": "帐篷休息是安全的"}, {"uid": "12041748", "content": "大吊男"}, {"uid": "5669525", "content": "23333"}, {"uid": "5669525", "content": "233"}, {"uid": "6531451", "content": "←+1"}, {"uid": "6531451", "content": "nern的a暴击率高啊"}, {"uid": "1669688", "content": "鹅的记忆"}, {"uid": "34815340", "content": "bye"}, {"uid": "11552854", "content": "不如RERRY"}, {"uid": "11552854", "content": "还没死。。。"}, {"uid": "11552854", "content": "表白老鹅，不服憋着"}, {"uid": "5734782", "content": "这是什么。。。"}, {"uid": "1292651", "content": "我睡的时候就只是有人对我放了一个屁…"}, {"uid": "11339573", "content": "啪"}, {"uid": "11339573", "content": "老哥   稳！"}, {"uid": "302350", "content": "23333333333333"}, {"uid": "23294529", "content": "23333"}, {"uid": "23294529", "content": "心疼"}, {"uid": "23294529", "content": "lisa"}, {"uid": "31620805", "content": "鹅的记忆"}, {"uid": "919488", "content": "TF（头发）BOY"}, {"uid": "39099445", "content": "瓦特？？"}, {"uid": "7970983", "content": "好污啊"}, {"uid": "7970983", "content": "233333333"}, {"uid": "4586681", "content": "233333333333"}, {"uid": "7970983", "content": "2333333333"}, {"uid": "7970983", "content": "2333333"}, {"uid": "7970983", "content": "233333333"}, {"uid": "13083924", "content": "拿着纸写下就好了啊"}, {"uid": "20745774", "content": "哈哈哈哈哈"}, {"uid": "2195110", "content": "23333333333"}, {"uid": "2195110", "content": "2333333"}, {"uid": "2195110", "content": "2333333"}, {"uid": "27652176", "content": "马铃薯酒"}, {"uid": "21369542", "content": "Terry回来啦"}, {"uid": "21369542", "content": "ewwa"}, {"uid": "20759887", "content": "好蓝啊"}, {"uid": "20759887", "content": "233333333"}, {"uid": "2195110", "content": "嗑药了吗那人……"}, {"uid": "2195110", "content": "233333"}, {"uid": "2195110", "content": "什么鬼2333"}, {"uid": "2195110", "content": "骑车爬绳子？！"}, {"uid": "2195110", "content": "233333"}, {"uid": "37189161", "content": "看不下去了。。。好蠢"}, {"uid": "22062521", "content": "咬你一口你就知道疼了，flag已立"}, {"uid": "22062521", "content": "其实换terry很好，nern升级后有加血有回蓝回怒气"}, {"uid": "22062521", "content": "这是老E直播后的录播"}, {"uid": "22062521", "content": "玩的时候也觉得是废话，后来救司机那里知道我错了"}, {"uid": "13683711", "content": "没有燃烧瓶过不了的，你不知道这个射弓箭的是有一个放火箭的技能吗？"}, {"uid": "304442", "content": "假胸"}, {"uid": "304442", "content": "hhhh这傻鹅"}, {"uid": "304442", "content": "这半藏好菜哦"}, {"uid": "13495170", "content": "只要前面多在勇者之路刷及，后面都很好过。"}, {"uid": "13495170", "content": "有车就快了"}, {"uid": "13495170", "content": "那个柴油机里做燃烧瓶"}, {"uid": "4693768", "content": "一只红色小蜘蛛跑过23333"}, {"uid": "35064358", "content": "大家别看了，后面就换游戏了"}, {"uid": "2032456", "content": "打"}, {"uid": "2032456", "content": "233333333333"}, {"uid": "2032456", "content": "五毛拿来"}, {"uid": "2032456", "content": "走了个DJ，来了个半藏"}, {"uid": "2032456", "content": "没有"}, {"uid": "8550101", "content": "。。"}, {"uid": "209598", "content": "2333"}, {"uid": "209598", "content": "果斷ww"}, {"uid": "11794229", "content": "BGM蜜汁拍手我开始抖腿"}, {"uid": "11794229", "content": "握草？一指禅伤害不错啊"}, {"uid": "11794229", "content": "然而刚刚你打怪给了一瓶"}, {"uid": "11794229", "content": "鹅的记忆只有7秒，dwwa"}, {"uid": "11794229", "content": "其实-_-||老E后期燃烧瓶A死了无数人"}, {"uid": "11794229", "content": "那个直接点的，就没有前几下的伤害了，只有最后一下"}, {"uid": "11794229", "content": "抢手伤害低-_-||但是暴击伤害特别高啊"}, {"uid": "3615056", "content": "秘籍：反复横跳！"}, {"uid": "36714709", "content": "鹅叫"}, {"uid": "36714709", "content": "鹅之惨叫"}, {"uid": "36714709", "content": "不如跳舞"}, {"uid": "36714709", "content": "鹅玩得好6啊"}, {"uid": "36714709", "content": "用肾记忆的老鹅2333"}, {"uid": "36714709", "content": "鹅的记忆只有三秒"}, {"uid": "36714709", "content": "鹅的记忆"}, {"uid": "36714709", "content": "不要啊 你这只怂鹅"}, {"uid": "36714709", "content": "麦半藏"}, {"uid": "2363543", "content": "因为胸太大而被当做女孩子"}, {"uid": "2363543", "content": "三句不离..."}, {"uid": "2363543", "content": "头发会害怕鬼故事吗"}, {"uid": "2363543", "content": "头发是个中指哈哈哈哈哈哈哈哈哈哈"}, {"uid": "8293867", "content": "不，仅仅是因为给你的燃烧瓶你不用"}, {"uid": "8293867", "content": "让你小气不用燃烧瓶"}, {"uid": "8293867", "content": "要变异了"}, {"uid": "8293867", "content": "我记得是姐姐啊"}, {"uid": "8293867", "content": "一片漆黑中我看到了一个光头"}, {"uid": "2363543", "content": "↓来呀大爷来玩呀"}, {"uid": "2363543", "content": "bard睡下去看起来被削成人棍了一样.."}, {"uid": "2110794", "content": "祖传燃烧瓶"}, {"uid": "2110794", "content": "祖传燃烧瓶"}, {"uid": "2110794", "content": "是你太抠啦"}, {"uid": "2110794", "content": "祖传燃烧瓶。"}, {"uid": "2110794", "content": "叫你不扔火瓶"}, {"uid": "2079653", "content": "23333"}, {"uid": "2079653", "content": "大笨鹅"}, {"uid": "3103993", "content": "23333333333"}, {"uid": "489212", "content": "进度条出卖了你"}, {"uid": "11895527", "content": "2333333333"}, {"uid": "11895527", "content": "233333333333"}, {"uid": "11351378", "content": "老鹅用肾记忆，很强"}, {"uid": "2709773", "content": "Yoooooooo~"}, {"uid": "7504373", "content": "233333333"}, {"uid": "7504373", "content": "两个玫瑰炸游戏"}, {"uid": "5850076", "content": "直接用技能少了很多伤害的"}, {"uid": "1961511", "content": "23333333333"}, {"uid": "2552393", "content": "叫你立flagz"}, {"uid": "2552393", "content": "第三个"}, {"uid": "12664774", "content": "2333333"}, {"uid": "11780943", "content": "第三"}, {"uid": "11780943", "content": "瞎鹅"}, {"uid": "11780943", "content": "瞎鹅"}, {"uid": "31849546", "content": "写福特是下车"}, {"uid": "11226511", "content": "要什么自行车233333"}, {"uid": "6710005", "content": "可以可以"}, {"uid": "6710005", "content": "噢，在这停顿"}, {"uid": "6710005", "content": "2333333"}, {"uid": "6710005", "content": "233333333"}, {"uid": "33393759", "content": "fa~fa fa fa"}, {"uid": "12891014", "content": "←没有燃烧瓶过不了好吗"}, {"uid": "12891014", "content": "说找自行车的，自行车就在那个boss后面"}, {"uid": "12891014", "content": "必须要燃烧瓶"}, {"uid": "12891014", "content": "这里必须要火焰瓶"}, {"uid": "12891014", "content": "勇士路要燃烧瓶才过得了"}, {"uid": "8586936", "content": "蛇还管你认怂？"}, {"uid": "8586936", "content": "这boss几千血啊"}, {"uid": "20219479", "content": "momoda"}, {"uid": "894005", "content": "刚右边是个女的？？？？"}, {"uid": "3430849", "content": "丢燃烧瓶就是布丢"}, {"uid": "3430849", "content": "到最后只有几个队友不会叛变"}, {"uid": "3430849", "content": "有赚翻了"}, {"uid": "3430849", "content": "然而最早的队友不会背叛"}, {"uid": "3430849", "content": "4个人群殴一个"}, {"uid": "36048912", "content": "老鹅忘记了往下跳"}, {"uid": "538965", "content": "哦!在这停顿!"}, {"uid": "1572045", "content": "在这停顿"}, {"uid": "1754038", "content": "霍金"}, {"uid": "1754038", "content": "被你抢先了"}, {"uid": "5929898", "content": "233333333"}, {"uid": "1729669", "content": "两个白人生出来个黑人"}, {"uid": "9165553", "content": "西方记者"}, {"uid": "9165553", "content": "肤浅那个你可以滚啊，又"}, {"uid": "1648721", "content": "其实技能里可以直接点2333"}, {"uid": "27103793", "content": "bgm蜜汁带感"}, {"uid": "9165553", "content": "身体老实得很"}, {"uid": "9165553", "content": "摸摸大肥鹅"}, {"uid": "9165553", "content": "这进度条良心"}, {"uid": "12331141", "content": "2"}, {"uid": "16020071", "content": "下去会被拉回来 重新挑战 还要五本书"}, {"uid": "16020071", "content": "曲"}, {"uid": "14970054", "content": "存活确认"}, {"uid": "5175847", "content": "总算想起了麦爹"}, {"uid": "11200468", "content": "存活"}, {"uid": "13828693", "content": "你吕儿"}, {"uid": "388018", "content": "卧槽"}, {"uid": "388018", "content": "23333333"}, {"uid": "2191854", "content": "头发：吓得我头发都立起来了"}, {"uid": "388018", "content": "又一次错过瓶子"}, {"uid": "388018", "content": "岛田雷"}, {"uid": "38296188", "content": "先睡一觉啊，至少这次醒来不会有人打劫也不会中毒"}, {"uid": "461781", "content": "怂鹅"}, {"uid": "32961049", "content": "2333333333333"}, {"uid": "1850982", "content": "最好把钱用完⋯⋯"}, {"uid": "1850982", "content": "睡觉人被拐了"}, {"uid": "1850982", "content": "有个地方可以装燃烧瓶，老e没去"}, {"uid": "1850982", "content": "100块都不给我"}, {"uid": "33769889", "content": "存活"}, {"uid": "1850982", "content": "giligili eye~"}, {"uid": "2890040", "content": "实力小龙虾"}, {"uid": "5658120", "content": "默默看下进度条。。"}, {"uid": "8802416", "content": "封面上上吊的是Lisa？"}, {"uid": "6313215", "content": "不用管，也就个弱鸡"}, {"uid": "6313215", "content": "麦克藏到后面要有神龙相助就厉害"}, {"uid": "10855178", "content": "弹幕开了？"}, {"uid": "16074948", "content": "那守望先锋呢？"}, {"uid": "16074948", "content": "↓葛优躺"}, {"uid": "12145429", "content": "laoe不舍的用，抠门鹅"}, {"uid": "12145429", "content": "woc老鹅反应好快啊"}, {"uid": "12145429", "content": "500多血很高呀，比你其他队友高好多好不"}, {"uid": "12145429", "content": "据说你已经把地形背下来了"}, {"uid": "12145429", "content": "进度条告诉了我一切"}, {"uid": "12145429", "content": "左边好像有其它的路"}, {"uid": "12145429", "content": "老鹅好像错过了一个瓶子"}, {"uid": "1545573", "content": "晚安"}, {"uid": "6112029", "content": "承包老鹅╭(╯ε╰)╮"}, {"uid": "11745051", "content": "就这样？"}, {"uid": "22236505", "content": "` `"}, {"uid": "4841766", "content": "老年人记忆衰退（手动滑稽）"}, {"uid": "20899847", "content": "问题来了，为什么说他多汁？"}, {"uid": "20899847", "content": "然后站起来再攻击直接秒人"}, {"uid": "20899847", "content": "要磕药再进"}, {"uid": "11538869", "content": "之前的拿枪好吧2333"}, {"uid": "11538869", "content": "升级成交通事故了2333"}, {"uid": "11538869", "content": "怂鹅"}, {"uid": "11538869", "content": "2333"}, {"uid": "13605975", "content": "真是瞎。。。"}, {"uid": "14699559", "content": "·    ·"}, {"uid": "13409782", "content": "被炸出来了哈哈"}, {"uid": "479113", "content": "2"}, {"uid": "479113", "content": "而且还很多zhi……"}, {"uid": "479113", "content": "是不是要买延长线 过桥？"}, {"uid": "479113", "content": "啊！爽！终于捡起来了"}, {"uid": "479113", "content": "找个本子记一下不好吗"}, {"uid": "7654863", "content": "鹅的记忆只有5秒"}, {"uid": "18983609", "content": "说实话，打小怪用技能有点浪费sp"}, {"uid": "12316267", "content": "弗莱迪？午夜后宫？"}, {"uid": "12316267", "content": "读档也没用了…心急啊…"}, {"uid": "8960268", "content": "前期神器！然而鹅不用"}, {"uid": "8960268", "content": "鹅的记忆"}, {"uid": "2559696", "content": "滚一边去！"}, {"uid": "20927545", "content": "弹幕？？"}, {"uid": "8960268", "content": "有人还记得前面来的时候在地下的小黄书吗"}, {"uid": "12316267", "content": "要出事啊感觉…老e太容易相信人了…"}, {"uid": "12316267", "content": "lisa三部相当奇怪的都没有完整攻略"}, {"uid": "6060663", "content": "神他喵跌倒"}, {"uid": "6060663", "content": "懵逼"}, {"uid": "6060663", "content": "没有上车快捷键吗"}, {"uid": "6060663", "content": "飞起来！！！！！！！"}, {"uid": "6060663", "content": "会不会醒来啥小黄书都没了"}, {"uid": "13652340", "content": "儿子"}, {"uid": "8209815", "content": "期望越大，失望越大，无人深空后来被老E喷成了翔。"}, {"uid": "20931494", "content": "第一眼看成"}, {"uid": "12316267", "content": "毕竟麦克藏随缘"}, {"uid": "12316267", "content": "哦拿酒来！"}, {"uid": "12316267", "content": "智慧的凝视（不"}, {"uid": "12316267", "content": "香烟解毒啊"}, {"uid": "10678739", "content": "233333333333"}, {"uid": "12316267", "content": "天哪这里好苏！好轻浮戏谑的感觉但是！我日老e我想嫁你！"}, {"uid": "12316267", "content": "那么问题来了dj和半藏谁比较强"}, {"uid": "12316267", "content": "鹅的记忆啊…之前有了啊"}, {"uid": "12316267", "content": "战旗直播啦。"}, {"uid": "12316267", "content": "没有脚本在老鹅啊…（么么"}, {"uid": "12316267", "content": "我开始怀疑大母鹅能不能记住了"}, {"uid": "12316267", "content": "低配麦爹"}, {"uid": "12316267", "content": "先去刷本小黄书"}, {"uid": "12316267", "content": "8.18的表示老e还打了第5天"}, {"uid": "12316267", "content": "说好的线下看剧情呢"}, {"uid": "12316267", "content": "惊了95分钟"}, {"uid": "13409782", "content": "23333333"}, {"uid": "13409782", "content": "实力眼瞎"}, {"uid": "2281520", "content": "弹幕呢？"}, {"uid": "7617917", "content": "橡树史蒂夫"}, {"uid": "24810790", "content": "硬控"}, {"uid": "7763165", "content": "我玩的时候被秒了啊"}, {"uid": "2055527", "content": "呆头鹅"}, {"uid": "2055527", "content": "读档。。。"}, {"uid": "2055527", "content": "用燃烧瓶啊"}, {"uid": "19758823", "content": "咪咪长背上了"}, {"uid": "1921853", "content": "麦克藏"}, {"uid": "293071", "content": "学多呀"}, {"uid": "293071", "content": "没头发了"}, {"uid": "293071", "content": "存档"}, {"uid": "7467953", "content": "提示而且啦，方便救司机"}, {"uid": "2055527", "content": "太好笑了哈哈哈哈哈哈哈哈"}, {"uid": "2055527", "content": "蓝骚瓶"}, {"uid": "2055527", "content": "身败名裂"}, {"uid": "2055527", "content": "2333333333333"}, {"uid": "2055527", "content": "还是dj吧"}, {"uid": "9992691", "content": "up残忍"}, {"uid": "9992691", "content": "真心有意思"}, {"uid": "9992691", "content": "是提供服务吧"}, {"uid": "4107780", "content": "233333333333333"}, {"uid": "4107780", "content": "23333333333333"}, {"uid": "4107780", "content": "2333333333333333"}, {"uid": "29400927", "content": "hh"}, {"uid": "29400927", "content": "我想看结局"}, {"uid": "29400927", "content": "帐篷里应该有人"}, {"uid": "29400927", "content": "2333"}, {"uid": "3170529", "content": "经纪人？"}, {"uid": "11065307", "content": "眼睛疼吗？"}, {"uid": "11065307", "content": "儿童自行车"}, {"uid": "11065307", "content": "彼此彼此"}, {"uid": "3170529", "content": "是太低级了"}, {"uid": "25818409", "content": "麦克藏也是靠随缘的暴击23333"}, {"uid": "11605143", "content": "233"}, {"uid": "5669308", "content": "23333333333333"}, {"uid": "11065307", "content": "有毒啊"}, {"uid": "11065307", "content": "怪物竟然怕鬼故事..."}, {"uid": "11065307", "content": "并没有"}, {"uid": "23682564", "content": "噫"}, {"uid": "4991228", "content": "无人升空就是垃圾"}, {"uid": "23682564", "content": "陪妹妹的给我滚过来，身为没有妹妹妹控不能忍"}, {"uid": "4107780", "content": "2333333333333333"}, {"uid": "3863511", "content": "打这里丢了好几个燃烧瓶"}, {"uid": "3863511", "content": "这里是可以赢的"}, {"uid": "23339298", "content": "跳着看2333333"}, {"uid": "20931494", "content": "开了疾步的76和不开疾步的76。2333"}, {"uid": "2388948", "content": "鹅好可爱"}, {"uid": "13153607", "content": "←一指禅"}, {"uid": "13153607", "content": "叫尼桑？"}, {"uid": "13809994", "content": "瓶子哭晕"}, {"uid": "13809994", "content": "车啊"}, {"uid": "11177280", "content": "2333"}, {"uid": "13809994", "content": "车啊"}, {"uid": "1394453", "content": "宝强，宋喆，马蓉"}, {"uid": "4107780", "content": "2333333333333333"}, {"uid": "5080877", "content": "这里有个洞"}, {"uid": "5080877", "content": "老E漏了一个洞"}, {"uid": "5080877", "content": "233"}, {"uid": "5080877", "content": "你傻你别走"}, {"uid": "4107780", "content": "233333333333333"}, {"uid": "4107780", "content": "鹅的记忆2333333333"}, {"uid": "14104686", "content": "不该吐槽，这是哪么..."}, {"uid": "14104686", "content": "终于不盖存档"}, {"uid": "14104686", "content": "盾牌"}, {"uid": "14104686", "content": "这就是盖存档的好处GG"}, {"uid": "14104686", "content": "蠢鹅"}, {"uid": "14104686", "content": "恕我直言，为啥不用燃烧瓶....."}, {"uid": "14104686", "content": "八个亚拉"}, {"uid": "14104686", "content": "规则都不看"}, {"uid": "17539008", "content": "."}, {"uid": "37725812", "content": "存活"}, {"uid": "37725812", "content": "存活"}, {"uid": "3517491", "content": "怎么打都是输的。。"}, {"uid": "3517491", "content": "直接去找泰山也就不用半藏了╭(￣▽￣)╯╧═╧"}, {"uid": "3517491", "content": "猎人不见了"}, {"uid": "36741460", "content": "地鼠hhhhhhhh"}, {"uid": "10776663", "content": "第3"}, {"uid": "10776663", "content": "dwwa…"}, {"uid": "10776663", "content": "低配麦克雷"}, {"uid": "7932198", "content": "屏幕里面出现了一个大帅b"}, {"uid": "27938436", "content": "真的，不骗你"}, {"uid": "13123216", "content": "其实多好看得"}, {"uid": "805591", "content": "湿湿的棍♂子"}, {"uid": "805591", "content": "情景喜剧的感觉。。好谜"}, {"uid": "12891014", "content": "麦克雷后期有个技能伤害超高，现在没用"}, {"uid": "13164874", "content": "那是一段燃烧生命的舞蹈"}, {"uid": "805591", "content": "233333333333"}, {"uid": "32423887", "content": "2333"}, {"uid": "13164874", "content": "2333"}, {"uid": "805591", "content": "难道就只有我觉得这个游戏还挺好玩的？？"}, {"uid": "805591", "content": "没事老鹅不着急"}, {"uid": "805591", "content": "23333333333333333"}, {"uid": "13905851", "content": "还有一个勇者之路你没去过老鹅"}, {"uid": "20102694", "content": "23333"}, {"uid": "9607132", "content": "阿三牌自行车"}, {"uid": "2398353", "content": "因为这个是战旗的直播间的录制，有即时弹幕的"}, {"uid": "1655252", "content": "鬼故事是:看一看进度条～"}, {"uid": "598411", "content": "hhhhhh"}, {"uid": "2977383", "content": "用火球 "}, {"uid": "2977383", "content": "这是持续回血啊"}, {"uid": "2089632", "content": "说香水的有认真看吗"}, {"uid": "19053526", "content": "蜜汁姿势"}, {"uid": "12895855", "content": "弹幕演员"}, {"uid": "36192653", "content": "23333"}, {"uid": "36192653", "content": "不容易啊。"}, {"uid": "19053526", "content": "x睡觉没了吧"}, {"uid": "19053526", "content": "23333333"}, {"uid": "5732356", "content": "不睡觉就要买香水复活"}, {"uid": "5732356", "content": "bgm停了2333"}, {"uid": "15486239", "content": "哦，在这停顿"}, {"uid": "2166332", "content": "燃烧瓶啊"}, {"uid": "2166332", "content": "233333333333333"}, {"uid": "15575462", "content": "先去给老头酒啊"}, {"uid": "2166332", "content": "23333333333"}, {"uid": "2166332", "content": "2333333"}, {"uid": "6300779", "content": "肉变器……"}, {"uid": "2166332", "content": "副c"}, {"uid": "13302010", "content": "自行车在boss后面"}, {"uid": "12875088", "content": "很多汁？什么意思？"}, {"uid": "8386446", "content": "八月十四号 老e还在玩"}, {"uid": "6662231", "content": "23333333"}, {"uid": "6662231", "content": "应该是嗑药进去"}, {"uid": "33406322", "content": "没人呢"}, {"uid": "19512565", "content": "鹅:叭  叭   叭"}, {"uid": "19512565", "content": "鹅:叭  叭  叭"}, {"uid": "19512565", "content": "里爸爸"}, {"uid": "19512565", "content": "加一"}, {"uid": "19512565", "content": "蜜汁音效"}, {"uid": "19512565", "content": "啊♂"}, {"uid": "19512565", "content": "。。"}, {"uid": "19512565", "content": "绳子啊"}, {"uid": "23667263", "content": "233333333"}, {"uid": "5752673", "content": "是你太贪了"}, {"uid": "17813453", "content": "FA~FA~"}, {"uid": "6523018", "content": "鹅的记忆"}, {"uid": "34203542", "content": "同问  直接下不行吗"}, {"uid": "1448054", "content": "困难模式有2污水"}, {"uid": "1448054", "content": "然而那是弓箭手 蛮强的"}, {"uid": "2242329", "content": "给杂志也会强制战斗的 要赢只能扔燃烧瓶"}, {"uid": "36792371", "content": "在这停顿"}, {"uid": "10761361", "content": "你傻那个hhhjh"}, {"uid": "37815084", "content": "有杂志不给"}, {"uid": "7635939", "content": "233333333"}, {"uid": "13426340", "content": "☜给钱"}, {"uid": "19922703", "content": "第3"}, {"uid": "19922703", "content": "头发手指"}, {"uid": "19922703", "content": "23333"}, {"uid": "3015337", "content": "怪异应该是降低攻击力"}, {"uid": "36797684", "content": "2333333 这是勇士之路调头吧。好那我调头了"}, {"uid": "15993876", "content": "摔♂跤"}, {"uid": "6944203", "content": "团灭"}, {"uid": "6944203", "content": "燃烧瓶啊"}, {"uid": "6944203", "content": " 进度条 顶住啊！！"}, {"uid": "6944203", "content": "？？？ 这不是一开始的好朋友之一么"}, {"uid": "6944203", "content": "？？？"}, {"uid": "6944203", "content": "哈哈哈哈哈"}, {"uid": "6944203", "content": "持续输出 爆发输出 控制 持续输出"}, {"uid": "6944203", "content": "真是惨"}, {"uid": "6944203", "content": "2333333"}, {"uid": "6944203", "content": "直接下去呀"}, {"uid": "6944203", "content": "啊？"}, {"uid": "6944203", "content": "233"}, {"uid": "6944203", "content": "23333333333333"}, {"uid": "6944203", "content": "2333"}, {"uid": "6944203", "content": "0000 167"}, {"uid": "10426146", "content": "2333333333333"}, {"uid": "10426146", "content": "DJ"}, {"uid": "10426146", "content": "233333333"}, {"uid": "10426146", "content": "yoooooooo"}, {"uid": "10426146", "content": "2333333333333"}, {"uid": "10426146", "content": "233333333333333333333333333"}, {"uid": "36094832", "content": "去可爱的勇者之路吧"}, {"uid": "13383141", "content": "觉得ipad炸的我也是"}, {"uid": "10426146", "content": "2333333333333333"}, {"uid": "36094832", "content": "⬅️不是是弹幕演员"}, {"uid": "7780381", "content": "存档狂魔"}, {"uid": "19332708", "content": "对的"}, {"uid": "25023653", "content": "打不过，给他杂志 反正就是杂志给他算了，"}, {"uid": "35954967", "content": "自挂东南枝"}, {"uid": "27741801", "content": "iPad炸的算我一个…"}, {"uid": "8279832", "content": "速度加快速度加快"}, {"uid": "7375718", "content": "骑车啊"}, {"uid": "35954967", "content": "错过了个瓶子"}, {"uid": "35954967", "content": "嘎嘣脆"}, {"uid": "4216450", "content": "进度条"}, {"uid": "4216450", "content": "塞翁失马233"}, {"uid": "1753247", "content": "因为爱老鹅，所以可以看这么久"}, {"uid": "37367726", "content": "眼瞎鹅 hhhh"}, {"uid": "24771234", "content": "他的妹妹叫你傻"}, {"uid": "37367726", "content": "要啥自行车"}, {"uid": "5952356", "content": "愚蠢的鹅"}, {"uid": "34892858", "content": "第＝"}, {"uid": "24764437", "content": "鹅哲智撸"}, {"uid": "23410274", "content": "老e看不见"}, {"uid": "24764437", "content": "吓得我把小鹅吐出来了"}, {"uid": "24764437", "content": "no no no乖乖吃鹅粮"}, {"uid": "6459224", "content": "先存档"}, {"uid": "24764437", "content": "老E看得见弹幕？"}, {"uid": "28935932", "content": "开门查水表"}, {"uid": "3025602", "content": "然后被打？"}, {"uid": "3025602", "content": "用完了"}, {"uid": "5343426", "content": "2333333333"}, {"uid": "3025602", "content": "大意了吧"}, {"uid": "3025602", "content": "杂志是什么玩意"}, {"uid": "5343426", "content": "23333333333"}, {"uid": "6812425", "content": "进度条要撑不下去啦"}, {"uid": "35378309", "content": "2333"}, {"uid": "34074080", "content": "←秒被打脸。"}, {"uid": "21236563", "content": "睡觉"}, {"uid": "21236563", "content": "输了。。不用燃烧瓶"}, {"uid": "36470570", "content": "存活"}, {"uid": "36470570", "content": "但又有了一个队友。。"}, {"uid": "27409728", "content": "傻鵝23333"}, {"uid": "36470570", "content": "纸条写的是什么?"}, {"uid": "36470570", "content": "直接跳下去不就行了？!"}, {"uid": "21236563", "content": "我觉得要出事。。"}, {"uid": "6532467", "content": "狠狠的立了个flag"}, {"uid": "6532467", "content": "hhhhhhh"}, {"uid": "21236563", "content": "那个地方别去啊。。"}, {"uid": "6532467", "content": "有提示用燃烧瓶啊"}, {"uid": "21236563", "content": "这里超级危险，怪都贼强，不骗你们，我打过的"}, {"uid": "6532467", "content": "233333"}, {"uid": "6532467", "content": "等级太低了"}, {"uid": "17836490", "content": "233333"}, {"uid": "24825864", "content": "23333333333333333"}, {"uid": "33532086", "content": "233333"}, {"uid": "12258879", "content": "嘿嘿嘿"}, {"uid": "35378309", "content": "23333"}, {"uid": "35378309", "content": "路人甲表示俺只想看剧情"}, {"uid": "10667511", "content": "放在第一个就是提醒你"}, {"uid": "27553057", "content": "第一"}, {"uid": "12258879", "content": "nern"}, {"uid": "12258879", "content": "dwwa"}, {"uid": "28996988", "content": "i wanna的坑。。。。"}, {"uid": "27553057", "content": "杂志？"}, {"uid": "1965212", "content": "被遗忘的麦克藏"}, {"uid": "27553057", "content": "睡觉啊"}, {"uid": "28996988", "content": "偷偷承包"}, {"uid": "1965212", "content": "dwwa。。。。。。啊受不了你了"}, {"uid": "25621029", "content": "我看到自行车了"}, {"uid": "27409728", "content": "哩這懶鵝"}, {"uid": "27409728", "content": "理這慫鵝23333"}, {"uid": "37438335", "content": "有人吗？"}, {"uid": "1965212", "content": "dwwa。。。。。啊我都背得了"}, {"uid": "3025602", "content": "这游戏打不过去。。。"}, {"uid": "18760787", "content": "哈哈哈像哈士奇"}, {"uid": "3069265", "content": "滚一边去！"}, {"uid": "18323563", "content": "你给头发讲鬼故事"}, {"uid": "18760787", "content": "啊 进去了啊"}, {"uid": "1285901", "content": "我鹅太可怜，给你个硬币"}, {"uid": "18760787", "content": "怂什么啊捞鹅"}, {"uid": "18760787", "content": "？？？"}, {"uid": "18760787", "content": "这个是之前抢东西的吗"}, {"uid": "18760787", "content": "一指弹"}, {"uid": "18760787", "content": "hahaha喜闻见乐"}, {"uid": "18323563", "content": "你还是爱玩，嘴上说不要身体却很诚实"}, {"uid": "24006964", "content": "是不是回酒馆了？"}, {"uid": "24006964", "content": "头发才是本体～"}, {"uid": "7092952", "content": "一口一个"}, {"uid": "24006964", "content": "十本杂志！！不是小黄书～"}, {"uid": "24006964", "content": "爬绳时自行车在背后"}, {"uid": "3053112", "content": "蠢鹅"}, {"uid": "8201983", "content": "哈哈哈哈哈哈哈莫名想笑"}, {"uid": "508679", "content": "帐篷里不看吗"}, {"uid": "508679", "content": "asd"}, {"uid": "21923682", "content": "骑车爬绳"}, {"uid": "14149064", "content": "心疼"}, {"uid": "37000569", "content": "会吐233"}, {"uid": "37000569", "content": "怂者支路"}, {"uid": "37000569", "content": "等着陪你啊。"}, {"uid": "14149064", "content": "dwwa"}, {"uid": "37000569", "content": "我居然觉得是我iPad炸了。。"}, {"uid": "21611603", "content": "把自己换掉"}, {"uid": "37088066", "content": "23333"}, {"uid": "37000569", "content": ".   ."}, {"uid": "37000569", "content": "50已到"}, {"uid": "37000569", "content": "青草池塘处处ha"}, {"uid": "37000569", "content": "当然都在陪e过七夕呀owo"}, {"uid": "641753", "content": "惊辣"}, {"uid": "641753", "content": "卡关鹅"}, {"uid": "17073069", "content": "车被偷 神作"}, {"uid": "25290464", "content": "23333333"}, {"uid": "25290464", "content": "那是杂志啦。。"}, {"uid": "1949273", "content": "hhhhhh"}, {"uid": "1949273", "content": "我是E爸爸的女儿"}, {"uid": "1949273", "content": "是麦克雷和半藏的儿子"}, {"uid": "1680244", "content": "我刚刚看到小黄书了"}, {"uid": "2292519", "content": "是杂志啊"}, {"uid": "1680244", "content": "我笑着看了下进度条"}, {"uid": "7831772", "content": "233333323333好带感"}, {"uid": "33833793", "content": "燃烧瓶正在哭泣"}, {"uid": "7407776", "content": "233333"}, {"uid": "7407776", "content": "2333333333"}, {"uid": "7407776", "content": "23333333"}, {"uid": "7407776", "content": "233333333"}, {"uid": "7407776", "content": "来点儿音乐！"}, {"uid": "7966384", "content": "存活"}, {"uid": "7966384", "content": "给杂志"}, {"uid": "7966384", "content": "233333333333"}, {"uid": "7966384", "content": "麦克藏：QAQ"}, {"uid": "7407776", "content": "老年鹅"}, {"uid": "7966384", "content": "2333333333"}, {"uid": "7966384", "content": "血多"}, {"uid": "7966384", "content": "半藏不见了"}, {"uid": "7966384", "content": "2333333333333333"}, {"uid": "7966384", "content": "233333333333333333333333"}, {"uid": "7966384", "content": "233333333"}, {"uid": "7966384", "content": "2333333333"}, {"uid": "7966384", "content": "233333"}, {"uid": "7966384", "content": "23333333333333"}, {"uid": "7966384", "content": "flay"}, {"uid": "7966384", "content": "八 巴"}, {"uid": "24744725", "content": "明明是DWWA"}, {"uid": "7966384", "content": "23333333333"}, {"uid": "24006964", "content": "刚刚注意有个小红点跑过去，应该是毒虫23333"}, {"uid": "7966384", "content": "yoooo"}, {"uid": "7966384", "content": "骑车睡觉"}, {"uid": "7966384", "content": "友谊的小车"}, {"uid": "7966384", "content": "速度好快！"}, {"uid": "7966384", "content": "2333333"}, {"uid": "33833793", "content": "走了个dj，来了个半藏"}, {"uid": "7966384", "content": "23333333"}, {"uid": "7966384", "content": "23333333333"}, {"uid": "7966384", "content": "好看+1"}, {"uid": "11177558", "content": "hh"}, {"uid": "7966384", "content": "233333"}, {"uid": "7966384", "content": "233333"}, {"uid": "7966384", "content": "23333333"}, {"uid": "7966384", "content": "23333333333"}, {"uid": "7966384", "content": "燃烧瓶"}, {"uid": "7966384", "content": "23333333333333333"}, {"uid": "7966384", "content": "对面：叫你刚刚吓我"}, {"uid": "7966384", "content": "好坏233333"}, {"uid": "7966384", "content": "哇！"}, {"uid": "7966384", "content": "鹅的记忆2333333"}, {"uid": "7966384", "content": "2333333333333333"}, {"uid": "7966384", "content": "2333333333333333"}, {"uid": "7966384", "content": "蛇蛇辣么可爱ヾ(Ő∀Ő๑)ﾉ"}, {"uid": "7966384", "content": "女鹅"}, {"uid": "7966384", "content": "前面半藏的23333333"}, {"uid": "7966384", "content": "23333333333333333333"}, {"uid": "7966384", "content": "2333333333333"}, {"uid": "641753", "content": "找张纸记下来啊蠢鹅"}, {"uid": "14780523", "content": "一指禅……"}, {"uid": "11719708", "content": "老年鹅的记忆"}, {"uid": "7966384", "content": "233333"}, {"uid": "7966384", "content": "2333333"}, {"uid": "641753", "content": "不如火球厉害啊"}, {"uid": "7966384", "content": "233333"}, {"uid": "8080490", "content": "\\(≧▽≦)/"}, {"uid": "7966384", "content": "23333"}, {"uid": "7966384", "content": "（*/∇＼*）"}, {"uid": "7966384", "content": "2333"}, {"uid": "23807253", "content": "麦克藏"}, {"uid": "22916985", "content": "就是刚刚汽车那里啊"}, {"uid": "8080490", "content": "2333333333"}, {"uid": "1570383", "content": "这不是往回走吗……"}, {"uid": "8080490", "content": "23333333"}, {"uid": "8200899", "content": "反正平a都是零伤害 为什么不直接用技能"}, {"uid": "13467296", "content": "你有杂志啊，10本杂志"}, {"uid": "8200899", "content": "可以读档啊"}, {"uid": "8080490", "content": "爽！"}, {"uid": "8200899", "content": "这里不是可以直接下去吗"}, {"uid": "23807253", "content": "我看到现在"}, {"uid": "23807253", "content": "疼的"}, {"uid": "23807253", "content": "又要摔"}, {"uid": "23807253", "content": "铝鹅"}, {"uid": "10022769", "content": "fa♂"}, {"uid": "4521733", "content": "啊，我要回去辣车"}, {"uid": "33620679", "content": "被红蜘蛛咬了"}, {"uid": "10086143", "content": "带着女朋友看老鹅(￣^￣)ゞ"}, {"uid": "8200899", "content": "这游戏太虐了"}, {"uid": "8080490", "content": "23333认怂吧"}, {"uid": "1844656", "content": "三巨头"}, {"uid": "12912869", "content": "哈哈哈学到了，以后跟人家打架先给他讲个鬼故事，怕的不行"}, {"uid": "30846118", "content": "是多在吗？少了射箭的"}, {"uid": "30846118", "content": "这是pp嘛"}, {"uid": "30846118", "content": "直接跳下去？"}, {"uid": "31448155", "content": "滚一边去"}, {"uid": "30846118", "content": "又要跳一边？"}, {"uid": "7407776", "content": "233333333"}, {"uid": "5343426", "content": "233333"}, {"uid": "30846118", "content": "23333"}, {"uid": "6114646", "content": "bgm给关掉了？"}, {"uid": "7407776", "content": "23333333"}, {"uid": "12912869", "content": "233333"}, {"uid": "7407776", "content": "233333333333"}, {"uid": "12912869", "content": "23333这么听话"}, {"uid": "773901", "content": "鹅的记忆"}, {"uid": "31448155", "content": "哈哈哈哈哈哈"}, {"uid": "30846118", "content": "闪了的事撸多了"}, {"uid": "31448155", "content": "嗯嗯"}, {"uid": "3205874", "content": "进度条"}, {"uid": "30846118", "content": "然而是你捡的"}, {"uid": "31448155", "content": "已经杀光了吧"}, {"uid": "25290464", "content": "DJ"}, {"uid": "30846118", "content": "酷 好像是持续回血"}, {"uid": "25290464", "content": "进度条"}, {"uid": "7467953", "content": "印度人教你怎么坐4个人23333"}, {"uid": "25290464", "content": "红光是费血了。。之前也是"}, {"uid": "25290464", "content": "金鹅"}, {"uid": "25290464", "content": "23333"}, {"uid": "5596036", "content": "那个是lisa"}, {"uid": "7467953", "content": "难道是哪个女孩"}, {"uid": "5596036", "content": "一开始的机油吧"}, {"uid": "25290464", "content": "麦克藏2333"}, {"uid": "5596036", "content": "再存别的档已经晚了！"}, {"uid": "13038683", "content": "香烟啊"}, {"uid": "5596036", "content": "完了你还存档了，没救了"}, {"uid": "30480005", "content": "我就觉得走错路了"}, {"uid": "5596036", "content": "他女儿叫buddy"}, {"uid": "8124922", "content": "他以前的朋友"}, {"uid": "30480005", "content": "恭喜老鹅获得马铃薯白酒"}, {"uid": "6689149", "content": "哈哈"}, {"uid": "9157512", "content": "哦 在这停顿！"}, {"uid": "30480005", "content": "上期不是说要找自行车吗"}, {"uid": "8124922", "content": "十本杂志"}, {"uid": "8124922", "content": "老鹅fa"}, {"uid": "5760705", "content": "你找到一个湿木条"}, {"uid": "17647792", "content": "233333好萌"}, {"uid": "17647792", "content": "我好喜欢这个BGM"}, {"uid": "10185281", "content": "小黄书"}, {"uid": "7831772", "content": "说走就走23333"}, {"uid": "8708423", "content": "摔♂跤"}, {"uid": "5760705", "content": "23333333"}, {"uid": "7291240", "content": "认怂→_→"}, {"uid": "17310415", "content": "去勇者之路啊"}, {"uid": "7291240", "content": "前面好萌的，口味真棒233"}, {"uid": "8124922", "content": "不要啊我想看他的一指禅"}, {"uid": "7291240", "content": "黑谷桐歌  哈哈23333"}, {"uid": "17310415", "content": "评论区有大体剧情科普"}, {"uid": "7291240", "content": "鹅的记忆只有三秒钟~"}, {"uid": "7291240", "content": "←对的我也记得"}, {"uid": "1893509", "content": "回忆杀"}, {"uid": "7291240", "content": "走错啦"}, {"uid": "34613", "content": "其实这个配置不错了，一个回血一个回SP2输出"}, {"uid": "1680196", "content": "我聋了？"}, {"uid": "7291240", "content": "昨天才看了第一期~"}, {"uid": "1893509", "content": "盲人游戏"}, {"uid": "1893509", "content": "独挡吧"}, {"uid": "1893509", "content": "早用燃烧瓶"}, {"uid": "17310415", "content": "春娥一上线"}, {"uid": "13668721", "content": "就应该把主角换掉的。"}, {"uid": "13606280", "content": "突破天际的进度条"}, {"uid": "1893509", "content": "在这停顿"}, {"uid": "8581823", "content": "存档了GG"}, {"uid": "1893509", "content": "有车快多了"}, {"uid": "398108", "content": "好蓝"}, {"uid": "1924393", "content": "读档呗"}, {"uid": "8581823", "content": "那么一辆车怎么载4个人的"}, {"uid": "23609193", "content": "果断认怂"}, {"uid": "23609193", "content": "老鹅一开始认为都没用都想换想了想发现哪个都换不掉"}, {"uid": "8581823", "content": "很好看的啊"}, {"uid": "12406046", "content": "噫"}, {"uid": "23609193", "content": "鹅の记忆上线"}, {"uid": "12406046", "content": "2333333"}, {"uid": "12406046", "content": "又是幻觉"}, {"uid": "6203060", "content": "鹅～！"}, {"uid": "12406046", "content": "woc"}, {"uid": "8581823", "content": "要燃烧瓶才能过吧"}, {"uid": "12406046", "content": "都存过档了"}, {"uid": "12406046", "content": "麦克藏不见了"}, {"uid": "12406046", "content": "没头发了……"}, {"uid": "12406046", "content": "233333"}, {"uid": "12406046", "content": "？？"}, {"uid": "12406046", "content": "2333333"}, {"uid": "12406046", "content": "头发是本体"}, {"uid": "12406046", "content": "233333333"}, {"uid": "12406046", "content": "⬅️不是lisa，lisa是主角妹妹，早自杀了"}, {"uid": "12406046", "content": "233"}, {"uid": "12406046", "content": "2333333"}, {"uid": "12406046", "content": "卧槽233333"}, {"uid": "16018045", "content": "谁在打我"}, {"uid": "12568505", "content": "雇佣麦克雷"}, {"uid": "12406046", "content": "就是不会下车233"}, {"uid": "10326188", "content": "老鹅：害怕"}, {"uid": "6203060", "content": "下牛！"}, {"uid": "12406046", "content": "23333333"}, {"uid": "13013407", "content": "疲劳驾驶"}, {"uid": "12406046", "content": "23333"}, {"uid": "12406046", "content": "好萌23333"}, {"uid": "12406046", "content": "23333"}, {"uid": "24252868", "content": "四个人骑一辆车"}, {"uid": "12406046", "content": "2333"}, {"uid": "12406046", "content": "woc"}, {"uid": "17088702", "content": "我记得很酷是持续回血，第一期的状态单里讲过"}, {"uid": "12406046", "content": "2333332"}, {"uid": "10326188", "content": "有燃烧瓶应该就可以了吧"}, {"uid": "829926", "content": "你对人家的头发讲鬼故事233333333"}, {"uid": "10477287", "content": "还会有灼烧效果吧"}, {"uid": "829926", "content": "老鹅好溜啊！"}, {"uid": "5751231", "content": "居然是半藏"}, {"uid": "33336541", "content": "声音好小啊"}, {"uid": "15860266", "content": "规则都不看→_→"}, {"uid": "15860266", "content": "爆菊吗233"}, {"uid": "22288969", "content": "少了一个呀！"}, {"uid": "829926", "content": "地上那个空瓶子不捡好难受啊啊啊啊啊啊啊"}, {"uid": "15860266", "content": "233"}, {"uid": "829926", "content": "一口闷"}, {"uid": "5596036", "content": "dwwa"}, {"uid": "5596036", "content": "酒战斗时候吃啊"}, {"uid": "5596036", "content": "前面红光一闪什么情况"}, {"uid": "11552513", "content": "hahaha"}, {"uid": "3069265", "content": "把主角换了"}, {"uid": "16679262", "content": "叫你覆盖存档。。。"}, {"uid": "3069265", "content": "肯定有阴谋"}, {"uid": "5596036", "content": "画风突变"}, {"uid": "4637643", "content": "前方高苏！！"}, {"uid": "7172199", "content": "陪妹妹"}, {"uid": "5596036", "content": "这个游戏结局超级致郁，而且即使到了结局仍旧一头雾水"}, {"uid": "15860266", "content": "2333333333333"}, {"uid": "12941854", "content": "哈哈哈"}, {"uid": "829926", "content": "鹅对枪手的爱"}, {"uid": "16679262", "content": "刚才我仿佛听到了存档的叫声"}, {"uid": "11136153", "content": "身败名裂，一败涂地鹅"}, {"uid": "19556429", "content": "麦克雷不见了"}, {"uid": "7172199", "content": "明明是WASD。。"}, {"uid": "5596036", "content": "啥都和紫苑镇扯可不是个好习惯"}, {"uid": "33791307", "content": "来个弹幕"}, {"uid": "1680244", "content": "口意，下牛"}, {"uid": "6390374", "content": "读档吧"}, {"uid": "12895380", "content": "才发现"}, {"uid": "5596036", "content": "科普，其实lisa有三部，这是第二部painful"}, {"uid": "19556429", "content": "嗑药现场"}, {"uid": "11236048", "content": "23333"}, {"uid": "6390374", "content": "燃烧瓶啊"}, {"uid": "6390374", "content": "燃烧瓶"}, {"uid": "6390374", "content": "哇～"}, {"uid": "6390374", "content": "啪啪啪啪啪"}, {"uid": "737572", "content": "DJ鹅"}, {"uid": "6390374", "content": "啊♂"}, {"uid": "6159202", "content": "头发才是本体"}, {"uid": "6390374", "content": "西方记者"}, {"uid": "15369323", "content": "鹅的记忆"}, {"uid": "16679262", "content": "自行车要打了那个肉球才有"}, {"uid": "6390374", "content": "23333"}, {"uid": "6390374", "content": "把换下来的卖掉啊"}, {"uid": "6390374", "content": "自行车爬绳子"}, {"uid": "6390374", "content": "蛇居然会跌倒"}, {"uid": "32848324", "content": "233"}, {"uid": "6390374", "content": "儿童鹅"}, {"uid": "8179887", "content": "刚才那个地方不是男主小时候被打的地方么。。。。"}, {"uid": "8535540", "content": "墙上还有血迹"}, {"uid": "1979060", "content": "燃烧瓶有用吗。"}, {"uid": "32848324", "content": "早用燃烧瓶早打完了"}, {"uid": "6390374", "content": "好菜啊2333"}, {"uid": "8535540", "content": "没发现麦爹没了吗"}, {"uid": "25326338", "content": "然后你看到了一张帅气的脸"}, {"uid": "6390374", "content": "差不多是只废鹅了"}, {"uid": "12941854", "content": "233333"}, {"uid": "13893004", "content": "麦克藏没了"}, {"uid": "25326338", "content": "又忘了23333"}, {"uid": "10477287", "content": "dwwa"}, {"uid": "1893509", "content": "23333333"}, {"uid": "6390374", "content": "好蓝啊"}, {"uid": "8542628", "content": "欸！"}, {"uid": "1893509", "content": "求你写个纸条吧"}, {"uid": "271847", "content": "肉山大魔王2333"}, {"uid": "19556429", "content": "老鹅，那个是麦克雷"}, {"uid": "6390374", "content": "GG"}, {"uid": "6390374", "content": "要GG的节奏啊"}, {"uid": "11488209", "content": "哈哈哈"}, {"uid": "6390374", "content": "WSD"}, {"uid": "8179887", "content": "23333"}, {"uid": "12406046", "content": "2333"}, {"uid": "8535540", "content": "半藏随缘箭能那么好中吗"}, {"uid": "6390374", "content": "我是谁，这里是哪里，我要到哪里去，我要干什么"}, {"uid": "19072358", "content": "他可以开那辆卡车"}, {"uid": "8535540", "content": "进度条又出卖了鹅"}, {"uid": "6390374", "content": "又走错了2333"}, {"uid": "32848324", "content": "你现在应该找自行车"}, {"uid": "8581823", "content": "说好的回血呢"}, {"uid": "6390374", "content": "身败名裂"}, {"uid": "19072358", "content": "是吗有改动"}, {"uid": "32848324", "content": "用用脑子2333"}, {"uid": "6390374", "content": "不是这里"}, {"uid": "16679262", "content": "把brad换掉吧"}, {"uid": "6390374", "content": "金鱼鹅"}, {"uid": "29226105", "content": "应该要磕药"}, {"uid": "13893004", "content": "233333333333"}, {"uid": "6390374", "content": "好怂啊2333"}, {"uid": "32769045", "content": "主角吧。。。。。(手动滑稽)"}, {"uid": "8581823", "content": "23333333333333333333333333333333"}, {"uid": "5185679", "content": "笑出声 略萌"}, {"uid": "8535540", "content": "然而进度条已经暴露了"}, {"uid": "19072358", "content": "注意，前方鹅叫高能"}, {"uid": "13893004", "content": "这就是，爱:D"}, {"uid": "2330448", "content": "回存单啊"}, {"uid": "19072358", "content": "本游戏唯一一个带感的BGM"}, {"uid": "1893509", "content": "寂静岭的世界"}, {"uid": "8949103", "content": "2333333333"}, {"uid": "1893509", "content": "把第三个换了吧"}, {"uid": "34788413", "content": "脏啊，这游戏"}, {"uid": "8949103", "content": "233333333"}, {"uid": "8949103", "content": "10本杂志"}, {"uid": "1893509", "content": "记不得3个字..."}, {"uid": "1893509", "content": "智商捉急啊"}, {"uid": "1521462", "content": "hhh"}, {"uid": "1893509", "content": "2333333"}, {"uid": "34788413", "content": "那是杂志"}, {"uid": "34788413", "content": "23333333"}, {"uid": "7695772", "content": "老年健忘鹅"}, {"uid": "5113719", "content": "233333"}, {"uid": "19072358", "content": "因为你给她戴了个面具"}, {"uid": "5457764", "content": "伤心地把半藏都吐了出来"}, {"uid": "13893004", "content": "?"}, {"uid": "3858021", "content": "好可怜的Lisa。。。。"}, {"uid": "5113719", "content": "送玫瑰炸游戏……可以的很强"}, {"uid": "8485645", "content": "哈哈"}, {"uid": "9314768", "content": "当天直播就只记得1000个呱和100个玫瑰"}, {"uid": "12895380", "content": "我23333333"}, {"uid": "5419502", "content": "鹅的记忆"}, {"uid": "7494704", "content": "23333333"}, {"uid": "13193779", "content": "承包鹅的笑声"}, {"uid": "14117615", "content": "2333333"}, {"uid": "33330248", "content": "正解ಥ_ಥ"}, {"uid": "21404903", "content": "233333好萌"}, {"uid": "4782335", "content": "真的是三头一体"}, {"uid": "37314148", "content": "蛇神他吗的会摔倒"}, {"uid": "7967324", "content": "233333"}, {"uid": "8020610", "content": "葛优躺"}, {"uid": "17938693", "content": "进度条出卖了鹅"}, {"uid": "2252573", "content": "尖叫鹅233333"}, {"uid": "32569330", "content": "23333"}, {"uid": "12167823", "content": "233333"}, {"uid": "4660534", "content": "小学鹅笑翻2333"}, {"uid": "2252573", "content": "眼瞎鹅"}, {"uid": "5521138", "content": "23333"}, {"uid": "4660534", "content": "表示看得也很捉急"}, {"uid": "11622477", "content": "香水啊"}, {"uid": "11622477", "content": "悲剧的鹅叫"}, {"uid": "3301203", "content": "燃烧瓶"}, {"uid": "13730222", "content": "实在太蠢了！！老鹅的记忆"}, {"uid": "18343048", "content": "射箭的没了"}, {"uid": "3301203", "content": "@某谜"}, {"uid": "11622477", "content": "好萌的鹅叫"}, {"uid": "3301203", "content": "只有牛肉干"}, {"uid": "13730222", "content": "flag飞"}, {"uid": "9986325", "content": "我的耳朵"}, {"uid": "2252573", "content": "老年鹅"}, {"uid": "3301203", "content": "hhhhhhhhhh"}, {"uid": "3301203", "content": "直接往下不行吗"}, {"uid": "8020610", "content": "那个工厂的门会不会是要嗑药才能进去？"}, {"uid": "7982633", "content": "好直接"}, {"uid": "3301203", "content": "收掉啊"}, {"uid": "32431057", "content": "2333"}, {"uid": "3301203", "content": "小学鹅"}, {"uid": "10434304", "content": "2333"}, {"uid": "3301203", "content": "23333333"}, {"uid": "22568691", "content": "233"}, {"uid": "22568691", "content": "鹅叫"}, {"uid": "3301203", "content": "疯狂迷路的鹅"}, {"uid": "17863549", "content": "一股弱者的气息"}, {"uid": "3301203", "content": "完辣"}, {"uid": "3301203", "content": "gg"}, {"uid": "3301203", "content": "hhhhhhh"}, {"uid": "3301203", "content": "233333333333"}, {"uid": "3301203", "content": "把那个没用的换了吧hhh"}, {"uid": "5416836", "content": "骑自行车飞跃悬崖"}, {"uid": "604951", "content": "233333333333333333"}, {"uid": "3301203", "content": "忘了hh"}, {"uid": "25337514", "content": "怂鹅"}, {"uid": "7853966", "content": "233333333"}, {"uid": "206582", "content": "23333"}, {"uid": "6663694", "content": "鹅的记忆hhhhhhhhh"}, {"uid": "604951", "content": "迷之沉默"}, {"uid": "6271153", "content": "2333333"}, {"uid": "15395360", "content": "承包七夕的大母鹅ww"}, {"uid": "8345912", "content": "紫苑镇……有点像"}, {"uid": "1476200", "content": "前十！"}, {"uid": "34829824", "content": "真是前十啊"}, {"uid": "32697777", "content": "进度条感人系列"}, {"uid": "7966384", "content": "稀饭这个游戏（*/∇＼*）"}, {"uid": "12048168", "content": "噫"}, {"uid": "23014661", "content": "哦   在这停顿"}, {"uid": "13495170", "content": "LISA一共两部，所谓3部是第二部的DLC"}, {"uid": "4379250", "content": "大光头↓"}, {"uid": "6944203", "content": "233"}, {"uid": "10086143", "content": "进度条感人"}, {"uid": "30846118", "content": "空降地址 95分23秒"}, {"uid": "14710611", "content": "95分钟。。。"}, {"uid": "8211415", "content": "黑暗中突然钻出一只大光头"}, {"uid": "11405805", "content": "低音感人"}, {"uid": "35378309", "content": "有"}, {"uid": "18760787", "content": "人比弹幕多系列"}, {"uid": "37000569", "content": "休想！"}, {"uid": "15395360", "content": "画风可爱"}, {"uid": "15395360", "content": "弹幕前十占位"}, {"uid": "30272697", "content": "表白a女神"}, {"uid": "36797684", "content": "进度条⊙▽⊙"}, {"uid": "18760787", "content": "蜜汁沉默"}, {"uid": "7966384", "content": "23333"}, {"uid": "35711341", "content": "五千"}, {"uid": "13503870", "content": "别表示了，管我什么事啊"}, {"uid": "2032456", "content": "在这停顿"}, {"uid": "4991228", "content": "打过去还要很久"}, {"uid": "23646980", "content": "哦啦哦啦"}, {"uid": "36285574", "content": "h很好玩的游戏"}, {"uid": "215757", "content": "解"}, {"uid": "12277005", "content": "诶Lisa？"}, {"uid": "37825428", "content": "彈幕大軍呢？"}, {"uid": "6663694", "content": "早早早"}, {"uid": "1984847", "content": "刷新出了什么ww"}, {"uid": "13809994", "content": "进度条可以拍电影了"}, {"uid": "19512565", "content": "四人帮"}, {"uid": "1854212", "content": "没有"}, {"uid": "24825864", "content": "23333333333"}, {"uid": "13467296", "content": "•    •"}, {"uid": "2090295", "content": "zzz"}, {"uid": "36175853", "content": "额"}, {"uid": "9182014", "content": "第七"}, {"uid": "34829824", "content": "第一"}, {"uid": "5585270", "content": "解"}, {"uid": "14828805", "content": "?"}, {"uid": "3691259", "content": "20"}, {"uid": "26117745", "content": "第五个弹幕"}, {"uid": "39498993", "content": "说话呀，说话呀，说话呀"}, {"uid": "28935932", "content": "有"}, {"uid": "5521138", "content": "没问题呀"}, {"uid": "3301203", "content": "好前啊"}, {"uid": "26117745", "content": "前十啊"}, {"uid": "36198183", "content": "第一"}, {"uid": "19512565", "content": "老e"}, {"uid": "9359415", "content": "就不能给弓箭手讨论技术加tp然后弓箭用爆炸箭吗，看着好气"}, {"uid": "282751081", "content": "要是有手机版一定要玩"}, {"uid": "8900445", "content": "玩的什么啊 一边干别的事吗"}, {"uid": "262292781", "content": "zwb?"}, {"uid": "20840469", "content": "哈哈哈哈哈哈哈哈哈哈哈哈逗死我了"}, {"uid": "2673184", "content": "规则都不看还行"}, {"uid": "2673184", "content": "浪费两个肉干"}, {"uid": "2673184", "content": "李这样会掉粉的"}, {"uid": "2673184", "content": "李是猪吧"}, {"uid": "6531451", "content": "←鹅早就换成电脑玩了。。。"}, {"uid": "6531451", "content": "不是它伤 是nern物防太低了 只有7"}, {"uid": "20775918", "content": ".    ."}, {"uid": "12787897", "content": " -----------------+ "}, {"uid": "17813453", "content": "戏命师的枪？"}, {"uid": "34549460", "content": "就是不用"}, {"uid": "34549460", "content": "还钱"}, {"uid": "35793114", "content": "这明明是半藏，他有弓"}, {"uid": "35793114", "content": "说wasd的打脸不，不懂就不要瞎说"}, {"uid": "5572231", "content": "第一个看完"}, {"uid": "26076553", "content": "我来证明你们开了弹幕"}]