[{"uid": "34722233", "content": "初中吧现在"}, {"uid": "34722233", "content": "我已经想到会变成啥了"}, {"uid": "130037282", "content": "随手画出来这么牛的鬼"}, {"uid": "4519779", "content": "很像"}, {"uid": "130037282", "content": "娃"}, {"uid": "130037282", "content": "只能说是自己的哇"}, {"uid": "479169254", "content": "笑死上了贼船但还没完全上"}, {"uid": "34722233", "content": "太累人了这小孩养的"}, {"uid": "14944083", "content": "睡醒了"}, {"uid": "174006748", "content": "早"}, {"uid": "34237849", "content": "早上好"}, {"uid": "130037282", "content": "笑死 上了贼船下不去了"}, {"uid": "130037282", "content": "被当成人渣一样看了"}, {"uid": "479169254", "content": "好吧"}, {"uid": "479169254", "content": "额"}, {"uid": "479169254", "content": "什么东西你是女的吧"}, {"uid": "479169254", "content": "？？？？？？？？？"}, {"uid": "1460525", "content": "我跟同事的女朋友睡过"}, {"uid": "479169254", "content": "你可以把它踹下床"}, {"uid": "479169254", "content": "这是真不老实"}, {"uid": "479169254", "content": "怎么说"}, {"uid": "130037282", "content": "一会儿手砸脸 一会儿腿踢人"}, {"uid": "130037282", "content": "真的折磨"}, {"uid": "130037282", "content": "想起以前和睡相差的朋友一起睡"}, {"uid": "130037282", "content": "草"}, {"uid": "130037282", "content": "好家伙 一万日元一会儿就吃完了"}, {"uid": "479169254", "content": "搜嘎"}, {"uid": "479169254", "content": "打哈切"}, {"uid": "34722233", "content": "灰常感谢谷露露rua赠送的1个小心心"}, {"uid": "34722233", "content": "灰常感谢谷露露rua赠送的3个辣条"}, {"uid": "130037282", "content": "这差不多是养了个人形哈士奇"}, {"uid": "479169254", "content": "你是真困啊"}, {"uid": "7507380", "content": "换了家马上送的"}, {"uid": "7507380", "content": "我还是点上了嘻嘻"}, {"uid": "130037282", "content": "笑死 根本是拆家"}, {"uid": "34722233", "content": "完了"}, {"uid": "387838939", "content": "真超能力"}, {"uid": "1460525", "content": "拆家"}, {"uid": "130037282", "content": "这是打扫的天才"}, {"uid": "34722233", "content": "被子：我免费啦！"}, {"uid": "387838939", "content": "天亮了"}, {"uid": "387838939", "content": "呐"}, {"uid": "34722233", "content": "？瞎想开始了"}, {"uid": "130037282", "content": "既视感"}, {"uid": "130037282", "content": "“再皮把你丢垃圾桶”"}, {"uid": "1460525", "content": "专业"}, {"uid": "7507380", "content": "只能换个了"}, {"uid": "11393528", "content": "早牛牛残影！"}, {"uid": "11393528", "content": "早上又牛啦！"}, {"uid": "34722233", "content": "默笙早牛牛"}, {"uid": "130037282", "content": "瞳神线算是最好笑的线了"}, {"uid": "130037282", "content": "12岁的年轻调酒师"}, {"uid": "130037282", "content": "大人の卑劣"}, {"uid": "34722233", "content": "大人的世界你不懂啊"}, {"uid": "34722233", "content": "牛蛙"}, {"uid": "130037282", "content": "屑 诗子 屑"}, {"uid": "11739836", "content": "调酒师，a炮头子"}, {"uid": "11739836", "content": "hhh猿哥"}, {"uid": "7507380", "content": "那就不整了"}, {"uid": "34722233", "content": "草"}, {"uid": "7507380", "content": "这个日式樱花薯条是啥啊"}, {"uid": "34722233", "content": "真去工作了啊"}, {"uid": "130037282", "content": "呜呜呜呜呜呜呜我的天使"}, {"uid": "107924025", "content": "被抢了"}, {"uid": "1920574", "content": "这"}, {"uid": "107924025", "content": "小天使好像拿去还帐"}, {"uid": "130037282", "content": "杏子是真的天使担当"}, {"uid": "130037282", "content": "天使！天使！我的天使！"}, {"uid": "130037282", "content": "最后要钱还是为了别人"}, {"uid": "130037282", "content": "抵制住了金钱的you huo"}, {"uid": "130037282", "content": "太强大了！"}, {"uid": "1460525", "content": "前方高能"}, {"uid": "130037282", "content": "丐帮还行"}, {"uid": "34722233", "content": "牛蛙"}, {"uid": "34722233", "content": "我曹"}, {"uid": "130037282", "content": "变团宠了"}, {"uid": "34722233", "content": "你家儿子会钢琴？弹一曲？"}, {"uid": "34722233", "content": "太真实了"}, {"uid": "34722233", "content": "草"}, {"uid": "130037282", "content": "流浪汉团体内也要好好处好关系呢"}, {"uid": "7507380", "content": "让我康康"}, {"uid": "7507380", "content": "是的捏"}, {"uid": "7507380", "content": "今天自己点外卖"}, {"uid": "7507380", "content": "今天吃啥捏"}, {"uid": "7507380", "content": "恰早饭了恰早饭了"}, {"uid": "130037282", "content": "妈咪捡破烂养我阿"}, {"uid": "7507380", "content": "冷冷 我捡破烂养你啊"}, {"uid": "107924025", "content": "流浪汉教出小天使"}, {"uid": "7507380", "content": "野性消费"}, {"uid": "130037282", "content": "有够牛的"}, {"uid": "130037282", "content": "一晚上玩了250万日元"}, {"uid": "107924025", "content": "250W"}, {"uid": "7507380", "content": "玩嗨了"}, {"uid": "7507380", "content": "哈哈哈"}, {"uid": "34722233", "content": "女三：不知前路为何"}, {"uid": "130037282", "content": "瞳神の疑惑"}, {"uid": "34722233", "content": "招"}, {"uid": "34722233", "content": "这就算找到人了？"}, {"uid": "34722233", "content": "牛蛙"}, {"uid": "130037282", "content": "瞳神の始"}, {"uid": "1460525", "content": "女三开始工作"}, {"uid": "6754927", "content": "当然呀。"}, {"uid": "6754927", "content": "撤~"}, {"uid": "6754927", "content": "残影安~"}, {"uid": "34722233", "content": "小Z晚安"}, {"uid": "6754927", "content": "能发弹幕 我很幸福。"}, {"uid": "6754927", "content": "撤了撤了~ 睡觉去了 阿冷晚安 各位晚安~"}, {"uid": "6425567", "content": "哪产的劣质产品"}, {"uid": "6754927", "content": "233333~"}, {"uid": "6425567", "content": "洗一下就废了"}, {"uid": "130037282", "content": "惨 杏子 惨"}, {"uid": "6425567", "content": "啥质量啊"}, {"uid": "7507380", "content": "回不去了"}, {"uid": "4519779", "content": "又多了个女儿"}, {"uid": "6754927", "content": "还是少女击剑"}, {"uid": "7507380", "content": "击剑"}, {"uid": "6754927", "content": "这段笑死了。"}, {"uid": "107924025", "content": "扭到脖子了"}, {"uid": "6425567", "content": "脖子断了"}, {"uid": "130037282", "content": "本质温情番"}, {"uid": "34722233", "content": "草"}, {"uid": "1460525", "content": "前方本剧最搞笑的地方"}, {"uid": "1460525", "content": "言灵术"}, {"uid": "130037282", "content": "剧情冲突让人觉得非常有趣"}, {"uid": "130037282", "content": "但是有很多让人会心一笑的那种级别"}, {"uid": "130037282", "content": "这番比较少那种让人爆笑不止的地方"}, {"uid": "34722233", "content": "草"}, {"uid": "11739836", "content": "搞笑的地方来了。"}, {"uid": "1460525", "content": "我就不一样了 我想rua大冷子猫耳"}, {"uid": "34722233", "content": "你想想，这是咕噜噜啊，这样的话就显得很正常"}, {"uid": "130037282", "content": "妈咪抱抱"}, {"uid": "7507380", "content": "冷冷可以这样掐我吗"}, {"uid": "34722233", "content": "阿姨他"}, {"uid": "34722233", "content": "我懂了，这番每个人被打都会说"}, {"uid": "130037282", "content": "这震一下好帅"}, {"uid": "14794340", "content": "好难啊"}, {"uid": "130037282", "content": "搞笑番是这样的"}, {"uid": "1460525", "content": "这番很穷的"}, {"uid": "130037282", "content": "不过能动画化被更多人喜欢我就已经很开心了"}, {"uid": "130037282", "content": "动画组各方面都中规中矩"}, {"uid": "130037282", "content": "全靠原作优秀的剧情了基本上"}, {"uid": "130037282", "content": "op比ed强一点 但是也一般般"}, {"uid": "1460525", "content": "小天使！"}, {"uid": "130037282", "content": "女二来啦！"}, {"uid": "130037282", "content": "我最喜欢的搞笑漫画之一了"}, {"uid": "130037282", "content": "终 结 者 "}, {"uid": "107924025", "content": "尿了"}, {"uid": "15349989", "content": "直接成蛹"}, {"uid": "130037282", "content": "确实挺恶心 草"}, {"uid": "34722233", "content": "灰常感谢SieistYoung赠送的14个小心心"}, {"uid": "130037282", "content": "但是原作我就非常喜欢"}, {"uid": "1460525", "content": "黄毛给我整哭过"}, {"uid": "130037282", "content": "虽然动画组一般"}, {"uid": "130037282", "content": "呜呜呜我真的好喜欢这个作品"}, {"uid": "130037282", "content": "这片歌一般般"}, {"uid": "15349989", "content": "(°∀°)ﾉ"}, {"uid": "15349989", "content": "谁家煮红薯粥糊了！"}, {"uid": "34722233", "content": "又要去买一把新刀了"}, {"uid": "15349989", "content": "给我来一口！"}, {"uid": "130037282", "content": "不愧是特级盖饭"}, {"uid": "130037282", "content": "我倒是对鱼子感觉一般般"}, {"uid": "15349989", "content": "睡了两分钟又又又又醒了"}, {"uid": "130037282", "content": "好喜欢鱼子"}, {"uid": "15349989", "content": "早"}, {"uid": "1460525", "content": "要是有灵魂弹幕就更好了"}, {"uid": "34722233", "content": "桔梗花早早早"}, {"uid": "15349989", "content": "来了来了"}, {"uid": "130037282", "content": "男主颜艺挺多的"}, {"uid": "34722233", "content": "咖啡早早早"}, {"uid": "130037282", "content": "碾压局"}, {"uid": "1460525", "content": "阿姨她"}, {"uid": "34722233", "content": "牛蛙"}, {"uid": "34722233", "content": "草"}, {"uid": "107924025", "content": "腿软"}, {"uid": "130037282", "content": "改成动画版省去了一些说明性的东西"}, {"uid": "130037282", "content": "设定普及一下反而方便观看"}, {"uid": "1460525", "content": "我记得还有个超能力女儿番 也特治愈"}, {"uid": "130037282", "content": "没事 这番搞笑的不是设定方面"}, {"uid": "107924025", "content": "一个人单挑所有"}, {"uid": "130037282", "content": "i平时主要负责组内财务工作"}, {"uid": "1767437", "content": "(:3[____] ♡z♡z♡Z♡"}, {"uid": "130037282", "content": "但是男主设定是战斗力很弱"}, {"uid": "107924025", "content": "女二挺好的"}, {"uid": "1460525", "content": "女二女三都是天使"}, {"uid": "130037282", "content": "二当家派他去"}, {"uid": "130037282", "content": "因为大当家被干了"}, {"uid": "1460525", "content": "这番贼治愈 "}, {"uid": "130037282", "content": "跟别的组打"}, {"uid": "130037282", "content": "这其实是温情番"}, {"uid": "130037282", "content": "这省多少施工费"}, {"uid": "1920574", "content": "哦哦哦哦"}, {"uid": "34722233", "content": "太好用了"}, {"uid": "107924025", "content": "这要吃多少工程款"}, {"uid": "130037282", "content": "从此走上包工头之路是吧"}, {"uid": "34722233", "content": "牛蛙"}, {"uid": "34722233", "content": "我曹"}, {"uid": "130037282", "content": "我也要这能力去搬砖"}, {"uid": "130037282", "content": "太方便了"}, {"uid": "130037282", "content": "不至于头头 目前差不多是三当家"}, {"uid": "1460525", "content": "好歹是黑·社·会头头"}, {"uid": "130037282", "content": "家具都炸碎了男主一点事没有"}, {"uid": "130037282", "content": "男主肉是动画界默认设定了吗"}, {"uid": "107924025", "content": "收个女儿拯救世界"}, {"uid": "34722233", "content": "重新装修吧"}, {"uid": "1460525", "content": "哈哈哈"}, {"uid": "130037282", "content": "翘晚自习"}, {"uid": "130037282", "content": "然后早退"}, {"uid": "130037282", "content": "睡到晚饭"}, {"uid": "130037282", "content": "中午睡午觉"}, {"uid": "130037282", "content": "睡到中午吃饭"}, {"uid": "130037282", "content": "睡"}, {"uid": "130037282", "content": "到教室就开始谁"}, {"uid": "1460525", "content": "女二那个表情历历在目"}, {"uid": "130037282", "content": "早上迟到"}, {"uid": "130037282", "content": "这上课状态让我想到我的高中"}, {"uid": "130037282", "content": "雏是真的能睡"}, {"uid": "130037282", "content": "当初在贴吧追漫画版的时候就贼喜欢"}, {"uid": "34722233", "content": "男主是里面的人"}, {"uid": "34722233", "content": "搜嘎"}, {"uid": "107924025", "content": "超能力女儿跟冷宝一样厉害"}, {"uid": "130037282", "content": "前几个字被b站改掉了"}, {"uid": "130037282", "content": "这番全名叫黑/社/会/的超能力女儿"}, {"uid": "34722233", "content": "大师兄晚安"}, {"uid": "24351856", "content": "要11点半了，溜了溜了，晚安啦各位"}, {"uid": "1460525", "content": "这番贼好看"}, {"uid": "34722233", "content": "灰常感谢風月さま赠送的1个小心心"}, {"uid": "1460525", "content": "哟"}, {"uid": "34722233", "content": "风月早早早"}, {"uid": "1460525", "content": "超能力女儿！"}, {"uid": "130037282", "content": "妈咪抱抱"}, {"uid": "130037282", "content": "就是要从小养到大才叫养娃"}, {"uid": "130037282", "content": "成年了那还叫养娃吗"}, {"uid": "130037282", "content": "那不行"}, {"uid": "130037282", "content": "太麻烦了"}, {"uid": "130037282", "content": "阻碍我养娃的主要障碍是照顾婴儿时期"}, {"uid": "130037282", "content": "要是我以后也能捡个娃就好了"}, {"uid": "34722233", "content": "对哦"}, {"uid": "130037282", "content": "太小的听不懂话"}, {"uid": "130037282", "content": "指小学起步"}, {"uid": "34722233", "content": "所以男主很有钱咩？"}, {"uid": "130037282", "content": "我也喜欢照顾小孩"}, {"uid": "130037282", "content": "莫名其妙当了爹"}, {"uid": "130037282", "content": "捡了个女儿"}, {"uid": "34722233", "content": "搜嘎"}, {"uid": "130037282", "content": "她只会意念移物"}, {"uid": "130037282", "content": "拼不起来"}, {"uid": "130037282", "content": "终 结 者"}, {"uid": "129904", "content": "？怕不是直播间要没"}, {"uid": "34722233", "content": "灰常感谢ぁぃぼ浅葱赠送的20个小心心"}, {"uid": "16811446", "content": "这番 可以的"}, {"uid": "4519779", "content": "是可以练腹肌的番"}, {"uid": "34722233", "content": "我要一边看番一边看你"}, {"uid": "34722233", "content": "不行不行"}, {"uid": "34722233", "content": "好耶，是我没看过的番"}, {"uid": "4519779", "content": "(●￣(ｴ)￣●)"}, {"uid": "4519779", "content": "_(:3」∠)_我准备好了"}, {"uid": "34722233", "content": "我已经在线上了"}, {"uid": "6754927", "content": "_(:3」∠)_"}, {"uid": "34722233", "content": "刷新啦！"}, {"uid": "34722233", "content": "5点啦！"}, {"uid": "6754927", "content": "话说今天看啥番~"}, {"uid": "387838939", "content": "山东大枣"}, {"uid": "387838939", "content": "青枣"}, {"uid": "6754927", "content": "_(:3」∠)_"}, {"uid": "387838939", "content": "红枣"}, {"uid": "387838939", "content": "大枣"}, {"uid": "387838939", "content": "早"}, {"uid": "6754927", "content": "_(:3」∠)_ 枣"}, {"uid": "34722233", "content": "雷宝早早早"}, {"uid": "387838939", "content": "早上好啊"}, {"uid": "6754927", "content": "能发弹幕了。枯了"}, {"uid": "6754927", "content": "这一刻等了好久了。。终于！"}, {"uid": "6754927", "content": "我刚回家。"}, {"uid": "6754927", "content": "哇。。终于。。"}, {"uid": "6754927", "content": "_(:3」∠)_ 残影早。"}, {"uid": "34722233", "content": "小ZZ早早早~"}, {"uid": "6754927", "content": "早上好冷子哥~"}, {"uid": "6754927", "content": "_(:3」∠)_ 噢糊~~~"}, {"uid": "11739836", "content": "不是虚拟歌姬唱的没内味"}, {"uid": "24351856", "content": "晚上好！残影，阿冷"}, {"uid": "34722233", "content": "晚好！"}, {"uid": "34722233", "content": "大师兄！"}, {"uid": "24351856", "content": "好耶！"}, {"uid": "24351856", "content": "可以发弹幕了？！"}, {"uid": "24351856", "content": "测试"}, {"uid": "11739836", "content": "点歌 722013"}, {"uid": "129904", "content": "哈哈 "}, {"uid": "34722233", "content": "砖哥早上晚"}, {"uid": "21629300", "content": "问问"}, {"uid": "21629300", "content": "没什么"}, {"uid": "21629300", "content": "不睡觉吗"}, {"uid": "21629300", "content": "你睡觉吗"}, {"uid": "11739836", "content": "我姑姑和我哥一个年纪，只是辈分大"}, {"uid": "34722233", "content": "\\牛蛙"}, {"uid": "11739836", "content": "但是我姑姑估计是车万人"}, {"uid": "11739836", "content": "我虽然只经历过末期"}, {"uid": "11739836", "content": "车万的歌估计我都听过不少"}, {"uid": "121372", "content": "毕竟我是车万人"}, {"uid": "11739836", "content": "感觉是很久以前的风格"}, {"uid": "11739836", "content": "这歌是不是也挺老的"}, {"uid": "491155380", "content": "冷冷的翅膀真好吃呀 每天不就翅膀下饭看番 我都不好意思呀 "}, {"uid": "34722233", "content": "累死个人"}, {"uid": "1920574", "content": "肝累了吗"}, {"uid": "34722233", "content": "灰常感谢Terry_Lulu赠送的24个小心心"}, {"uid": "174006748", "content": "俺又来了"}, {"uid": "34722233", "content": "灰常感谢赛巴斯将蓝赠送的35个B坷垃"}, {"uid": "34722233", "content": "灰常感谢Ha_py残影赠送的2个辣条、24个小心心"}, {"uid": "34722233", "content": "灰常感谢風月さま赠送的1个小心心"}, {"uid": "7507380", "content": "干杯"}, {"uid": "7507380", "content": "好看的"}, {"uid": "7507380", "content": "可以"}, {"uid": "7507380", "content": "！"}, {"uid": "121372", "content": "点歌 32046789"}, {"uid": "7507380", "content": "今天看啥来着"}, {"uid": "7507380", "content": "太憨太憨了"}, {"uid": "7507380", "content": "冷子哥卖个萌"}, {"uid": "121372", "content": "点歌 751472"}, {"uid": "7507380", "content": "=V="}, {"uid": "7507380", "content": "OVO"}, {"uid": "121372", "content": "听歌呗"}, {"uid": "121372", "content": "我失眠了"}, {"uid": "121372", "content": "。。。额"}, {"uid": "121372", "content": "点歌 492053"}, {"uid": "121372", "content": "点歌 22644062"}, {"uid": "121372", "content": "点歌 26454912"}, {"uid": "121372", "content": "晚上好"}, {"uid": "34722233", "content": "将蓝晚好"}, {"uid": "121372", "content": "晚上好"}, {"uid": "121372", "content": "nya"}, {"uid": "34722233", "content": "点歌 138307"}, {"uid": "107924025", "content": "嘎嘣脆，鸡肉味，又是鸡块？"}, {"uid": "34722233", "content": "这是午饭"}, {"uid": "107924025", "content": "在吃宵夜？"}, {"uid": "4456301", "content": "阿巴阿巴"}, {"uid": "15349989", "content": "吧唧吧唧吧唧"}, {"uid": "11739836", "content": "嘴巴一开一合的哈哈哈"}, {"uid": "451791599", "content": "黎耶 辛苦了～"}, {"uid": "34722233", "content": "黎耶晚安"}, {"uid": "451791599", "content": "(°∀°)ﾉ"}, {"uid": "34722233", "content": "灰常感谢黎耶赠送的10个冰阔落"}, {"uid": "15349989", "content": "有一段时间天天炸"}, {"uid": "15349989", "content": "╮(￣▽￣)╭"}, {"uid": "15349989", "content": "破站炸了没什么奇怪"}, {"uid": "34722233", "content": "就是更新而已"}, {"uid": "34722233", "content": "没怎么"}, {"uid": "4456301", "content": "昨天b站怎么了"}, {"uid": "15349989", "content": "我的钟只有八点"}, {"uid": "4456301", "content": "（⌒▽⌒）"}, {"uid": "15349989", "content": "差点被家里抓"}, {"uid": "34722233", "content": "哦"}, {"uid": "34722233", "content": "八点？"}, {"uid": "15349989", "content": "刚刚差点被抓"}, {"uid": "15349989", "content": "起来嗨"}, {"uid": "15349989", "content": "才八点"}, {"uid": "1920574", "content": "我也去弄碗粥"}, {"uid": "38134407", "content": "直接晚安"}, {"uid": "38134407", "content": "晚好就算了"}, {"uid": "34722233", "content": "黑鳄晚安"}, {"uid": "38134407", "content": "该睡了 晚安"}, {"uid": "34722233", "content": "黑鳄晚好"}, {"uid": "34722233", "content": "所以我确实很聪明"}, {"uid": "34722233", "content": "XD"}, {"uid": "34722233", "content": "就很聪明"}, {"uid": "1920574", "content": "草"}, {"uid": "1920574", "content": "前两天不能suo话"}, {"uid": "34722233", "content": "灰常感谢橘猫型橘猫赠送的24个小心心、75个辣条"}, {"uid": "1920574", "content": "我也饿了 刚起来"}, {"uid": "11739836", "content": "点歌 31140699"}, {"uid": "34722233", "content": "阿冷拿外卖去了"}, {"uid": "34722233", "content": "terry晚好"}, {"uid": "1920574", "content": "啊 我终于被放出来了"}, {"uid": "1920574", "content": "阿巴阿巴"}, {"uid": "11739836", "content": "点歌 22677309"}, {"uid": "34722233", "content": "（）"}, {"uid": "34722233", "content": "去吧去吧"}, {"uid": "34722233", "content": "肝的东西先从等级开始"}, {"uid": "34722233", "content": "我反正是冲级型的选手"}, {"uid": "34722233", "content": "晚上早"}, {"uid": "697044811", "content": "您早上好"}, {"uid": "34722233", "content": "现在"}, {"uid": "34722233", "content": "不到10个"}, {"uid": "34722233", "content": "长期做完 了 快"}, {"uid": "34722233", "content": "是的"}, {"uid": "9822386", "content": "怪不得半天没说话了"}, {"uid": "34722233", "content": "那没事了"}, {"uid": "34722233", "content": "哦"}, {"uid": "34722233", "content": "麦……？"}, {"uid": "34722233", "content": "灰常感谢SieistYoung赠送的10个小心心"}, {"uid": "34722233", "content": "回来啦"}, {"uid": "34722233", "content": "灰常感谢真让超超摸不着头脑i赠送的1个冰阔落"}, {"uid": "735320742", "content": "睡了"}, {"uid": "735320742", "content": "点歌  快乐星猫"}, {"uid": "34722233", "content": "晚安晚安"}, {"uid": "34722233", "content": "嗯呐"}, {"uid": "735320742", "content": "那早上七点八点见"}, {"uid": "34722233", "content": "阿冷拿外卖去了"}, {"uid": "34722233", "content": "超超晚安"}, {"uid": "735320742", "content": "腾"}, {"uid": "34722233", "content": "去拿吧"}, {"uid": "34722233", "content": "那咋办"}, {"uid": "34722233", "content": "万一给吃了"}, {"uid": "9822386", "content": "还没到那也太菜了"}, {"uid": "34722233", "content": "噗"}, {"uid": "9822386", "content": "冷子哥外卖还没到？"}, {"uid": "735320742", "content": "吧"}, {"uid": "735320742", "content": "高町你不睡觉是"}, {"uid": "294955251", "content": "那我滚了"}, {"uid": "34722233", "content": "做梦就好了"}, {"uid": "130037282", "content": "如何短时间提高四百分"}, {"uid": "34722233", "content": "有办法的"}, {"uid": "9822386", "content": "毕竟是呜米"}, {"uid": "9822386", "content": "我感觉也蛮有可能的"}, {"uid": "294955251", "content": "问:如何在短时间内提高40分"}, {"uid": "9822386", "content": "放轮播的人挺多的，被封的就她一个"}, {"uid": "34722233", "content": "谢谢和蔼可亲老奶奶的关注，谢谢"}, {"uid": "11739836", "content": "可惜"}, {"uid": "9822386", "content": "呜米确实是被封了，但不知道是因为什么被封"}, {"uid": "11739836", "content": "高二想去考中科大的少年班"}, {"uid": "130037282", "content": "考点饿魔项目"}, {"uid": "34722233", "content": "回来啦"}, {"uid": "9822386", "content": "我回来了"}, {"uid": "130037282", "content": "不忽悠 真去魔界考试"}, {"uid": "294955251", "content": "/game easy"}, {"uid": "294955251", "content": "Enter: /remake"}, {"uid": "130037282", "content": "目前分数勉强大专 想考清华"}, {"uid": "294955251", "content": "贫穷的我只能抓只蛆撕点脚皮蘸着吃"}, {"uid": "130037282", "content": "我要去参加饿魔高考"}, {"uid": "130037282", "content": "妈咪 后天就高考了"}, {"uid": "294955251", "content": "是这个点吧"}, {"uid": "294955251", "content": "该点外卖吃了"}, {"uid": "34722233", "content": "看你做到哪了"}, {"uid": "34722233", "content": "就是好感等级的任务"}, {"uid": "34722233", "content": "灰常感谢風月さま赠送的1个小心心"}, {"uid": "34722233", "content": "正好就28级了，我吃了以后"}, {"uid": "240648332", "content": "账号注销只能看到牌子"}, {"uid": "34722233", "content": "就是长期任务里的"}, {"uid": "34722233", "content": "你看那个社交任务"}, {"uid": "34722233", "content": "我把好感的任务做了好多"}, {"uid": "34722233", "content": "应该最高27级又四分之五"}, {"uid": "34722233", "content": "但是我不知道为什么你的好感没有那么高的话"}, {"uid": "240648332", "content": "看不到"}, {"uid": "240648332", "content": "错  误 代  嘛 -4  灵 4"}, {"uid": "34722233", "content": "是的"}, {"uid": "92694259", "content": "不摸鱼还叫上班嘛"}, {"uid": "174006748", "content": "特无聊"}, {"uid": "174006748", "content": "闲时间就不知道干嘛"}, {"uid": "174006748", "content": "有事做，但是很闲"}, {"uid": "174006748", "content": "是今晚感觉特无聊"}, {"uid": "174006748", "content": "不夜班你看不到我"}, {"uid": "1915239", "content": "点歌 Hz:52"}, {"uid": "174006748", "content": "夜班啊"}, {"uid": "240648332", "content": "我就看到账号已注销"}, {"uid": "174006748", "content": "还是感觉好无聊啊"}, {"uid": "240648332", "content": "不知道啊"}, {"uid": "240648332", "content": "我都不记得是谁"}, {"uid": "11739836", "content": "所以看整活我只看外国的那只粉猫"}, {"uid": "1915239", "content": "晚上好！"}, {"uid": "9822386", "content": "顺便看看还有没有别的被封了的"}, {"uid": "240648332", "content": "那个牌子啊"}, {"uid": "11739836", "content": "这方面国内还是比较拘谨"}, {"uid": "9822386", "content": "我去点下牌子"}, {"uid": "9822386", "content": "看了一下，确实被封了"}, {"uid": "11739836", "content": "我只看过他们的切片"}, {"uid": "240648332", "content": "乌咪？"}, {"uid": "9822386", "content": "真的假的"}, {"uid": "9822386", "content": "听说呜米轮播被封了？"}, {"uid": "9822386", "content": "蝗虫产的卵鼹鼠都吃，怎么可能打不过蝗虫"}, {"uid": "240648332", "content": "一个月没看 晚上还是d不到人"}, {"uid": "11739836", "content": "不能放着直播看视频了"}, {"uid": "9822386", "content": "鼹鼠也是食虫目的，不是专门吃虫子？"}, {"uid": "34722233", "content": "制"}, {"uid": "34722233", "content": "限"}, {"uid": "34722233", "content": "升到"}, {"uid": "34722233", "content": "第一个"}, {"uid": "34722233", "content": "都是"}, {"uid": "34722233", "content": "我一直"}, {"uid": "34722233", "content": "嘶"}, {"uid": "34722233", "content": "XD"}, {"uid": "34722233", "content": "我从一开始就没看过剧情"}, {"uid": "9822386", "content": "这船不上也罢"}, {"uid": "29678426", "content": "(>_>)"}, {"uid": "29678426", "content": "我到底图个啥"}, {"uid": "29678426", "content": "我看了一下，舰长得到22年9月"}, {"uid": "9822386", "content": "跟咕噜噜那没法比"}, {"uid": "9822386", "content": "我顶多算偶尔顺便D"}, {"uid": "294955251", "content": "真好玩嘻嘻"}, {"uid": "294955251", "content": "乱打看出什么歌"}, {"uid": "130037282", "content": "建议人人戴上我晕"}, {"uid": "9822386", "content": "我又不是职业DD，不至于"}, {"uid": "130037282", "content": "我晕22"}, {"uid": "294955251", "content": "点歌 9467315"}, {"uid": "240648332", "content": "好家伙"}, {"uid": "130037282", "content": "最近懒得d了"}, {"uid": "130037282", "content": "我牌子只剩十几个亮着了"}, {"uid": "240648332", "content": "我都不想点了"}, {"uid": "240648332", "content": "我住院一个月百多个牌子全黑了"}, {"uid": "34722233", "content": "就很烦"}, {"uid": "294955251", "content": "点歌 冷冷"}, {"uid": "34722233", "content": "我不知道他主线是每天开启一点还是每天就只能做一点"}, {"uid": "294955251", "content": "点歌 我爱你"}, {"uid": "130037282", "content": "想睡又不想睡"}, {"uid": "9822386", "content": "我牌子都灭了，就只剩三五个了"}, {"uid": "130037282", "content": "妈咪我的妈咪"}, {"uid": "15349989", "content": "醒了"}, {"uid": "34722233", "content": "把其他的搞了再说= ="}, {"uid": "15349989", "content": "又又又"}, {"uid": "34722233", "content": "我感觉那个厨师等级可以先不急"}, {"uid": "15349989", "content": "好耶！"}, {"uid": "240648332", "content": " 因为你摩尔庄园一天很充实"}, {"uid": "130037282", "content": "点歌 34204085"}, {"uid": "174006748", "content": "让我顺着牌子去看看有哪个女人在播"}, {"uid": "174006748", "content": "好像有点无聊"}, {"uid": "29678426", "content": "吐了卡这么久"}, {"uid": "130037282", "content": "点歌 默"}, {"uid": "9822386", "content": "你不是说直播分心了摩尔庄园都打不完了吗"}, {"uid": "130037282", "content": "点歌 花女"}, {"uid": "9822386", "content": "以后专门打摩尔庄园不直播了是吧"}, {"uid": "130037282", "content": "省省肝吧妈咪"}, {"uid": "34722233", "content": "社交的经验"}, {"uid": "34722233", "content": "那你没有拿那些经验喽"}, {"uid": "34722233", "content": "啊？"}, {"uid": "9822386", "content": "买东西好感度涨得快正常"}, {"uid": "34722233", "content": "你现在有几个5级好感度的"}, {"uid": "11739836", "content": "点歌 父亲写的散文诗，许飞"}, {"uid": "130037282", "content": "今天有画画环节吗"}, {"uid": "34722233", "content": "这只能问策划了"}, {"uid": "9822386", "content": "小凡又开始了"}, {"uid": "130037282", "content": "点歌 世上只有妈妈好"}, {"uid": "130037282", "content": "点歌 左手右手"}, {"uid": "130037282", "content": "点歌 我会自己上厕所"}, {"uid": "130037282", "content": "点歌 不可解"}, {"uid": "130037282", "content": "点歌 群青"}, {"uid": "130037282", "content": "点歌 白日"}, {"uid": "130037282", "content": "嗯嗯"}, {"uid": "130037282", "content": "好耶 现在点歌正常了"}, {"uid": "130037282", "content": "点歌 one last kiss"}, {"uid": "130037282", "content": "黑听了几个小时orz"}, {"uid": "130037282", "content": "妈咪抱抱"}, {"uid": "29678426", "content": "点了多少钱"}, {"uid": "29678426", "content": "这能忍？"}, {"uid": "29678426", "content": "想搞点快乐水"}, {"uid": "29678426", "content": "恰完好久了"}, {"uid": "34722233", "content": "灰常感谢手つかずの感情赠送的2个辣条"}, {"uid": "9822386", "content": "兄弟叫我打枪我都没去，光顾着搓手机了"}, {"uid": "11739836", "content": "新番的ed都没听出来"}, {"uid": "11739836", "content": "86卧槽，怪不得我说我好像听过"}, {"uid": "9822386", "content": "辣鸡游戏害人"}, {"uid": "9822386", "content": "打坎公骑"}, {"uid": "9822386", "content": "好多天没D了"}, {"uid": "34722233", "content": "22小时，900份"}, {"uid": "9822386", "content": "我又有好多牌子黑了"}, {"uid": "34722233", "content": "是的"}, {"uid": "34722233", "content": "懂不懂"}, {"uid": "34722233", "content": "动不动"}, {"uid": "34722233", "content": "钱要用在刀刃上"}, {"uid": "34722233", "content": "80金豆而已"}, {"uid": "34722233", "content": "拿了三个河童"}, {"uid": "34722233", "content": "甩了三次渔网"}, {"uid": "170228481", "content": "今天也是钓粑粑海肠的一天"}, {"uid": "34722233", "content": "我在自己家掉"}, {"uid": "11739836", "content": "啥的ed"}, {"uid": "9822386", "content": "夺人所爱这个人指什么，翻译翻译"}, {"uid": "29678426", "content": "点歌 35040542"}, {"uid": "29678426", "content": "ed"}, {"uid": "9822386", "content": "夺人所爱什么意思？能不能给翻译翻译？"}, {"uid": "11739836", "content": "不是，这个是不是op或者ed啊"}, {"uid": "34722233", "content": "夺人所爱"}, {"uid": "11739836", "content": "这歌怎么感觉我看过"}, {"uid": "9822386", "content": "？？？"}, {"uid": "170228481", "content": "（）"}, {"uid": "29678426", "content": "（）"}, {"uid": "29678426", "content": "奎哥跟我跑了"}, {"uid": "170228481", "content": "？"}, {"uid": "34722233", "content": "是的"}, {"uid": "170228481", "content": "咕噜噜我的咕噜噜"}, {"uid": "11739836", "content": "这名字，代理了个寂寞"}, {"uid": "9822386", "content": "想吃就点，民以食为天。吃饭还怕人骂？"}, {"uid": "240648332", "content": "对不起 没蚌住"}, {"uid": "240648332", "content": "好残忍"}, {"uid": "7507380", "content": "_(:3」∠)_"}, {"uid": "34722233", "content": "人话？"}, {"uid": "7507380", "content": "我也想吃 "}, {"uid": "9822386", "content": "冷子哥直播间又热门了"}, {"uid": "240648332", "content": "这歌 NASA君？"}, {"uid": "9822386", "content": "冷子哥要不要，给你点一份"}, {"uid": "9822386", "content": "加若干小吃"}, {"uid": "9822386", "content": "我点了份纯猪肉馅的干捞水饺"}, {"uid": "240648332", "content": "能睡但没必要"}, {"uid": "9822386", "content": "困了，但没完全困"}, {"uid": "240648332", "content": "没蚌住"}, {"uid": "240648332", "content": "下午回来直接就睡沙发上了"}, {"uid": "11739836", "content": "因为太无聊了"}, {"uid": "11739836", "content": "上课对我来说就是折磨"}, {"uid": "11739836", "content": "睡五六个小时"}, {"uid": "240648332", "content": "我今天早上睡了4个小时"}, {"uid": "34722233", "content": "XD"}, {"uid": "34722233", "content": "早上七点起来"}, {"uid": "34722233", "content": "你看我前几周老是凌晨2点睡"}, {"uid": "29678426", "content": "我睡6小时是最好的"}, {"uid": "29678426", "content": "你能扛得住就行"}, {"uid": "170228481", "content": "懂了，你以后别睡了，连播"}, {"uid": "34722233", "content": "睡五个小时是最好的"}, {"uid": "34722233", "content": "我认为"}, {"uid": "11739836", "content": "正常，但没完全正常"}, {"uid": "29678426", "content": "我打包票了（）"}, {"uid": "170228481", "content": "就算我不正常也要看冷冷"}, {"uid": "34722233", "content": "不然我就说出来了"}, {"uid": "29678426", "content": "在座就没有正常的"}, {"uid": "34722233", "content": "还好你说的快"}, {"uid": "29678426", "content": "阴间战神冷子哥"}, {"uid": "9822386", "content": "我整点饺子"}, {"uid": "34722233", "content": "英国没有喷射战士吃"}, {"uid": "34722233", "content": "可惜了"}, {"uid": "29678426", "content": "草了，这也能第一"}, {"uid": "11739836", "content": "指我和喷射战士贴贴"}, {"uid": "11739836", "content": "吃喷射战士，贴贴"}, {"uid": "29678426", "content": "喷射战士是吧"}, {"uid": "29678426", "content": "兄弟们都没得看"}, {"uid": "19990666", "content": "懂了，50是车费"}, {"uid": "29678426", "content": "？？？？"}, {"uid": "29678426", "content": "我怎么可能拍"}, {"uid": "9822386", "content": "给我整饿了。冷子哥吃什么给我也点一份吧"}, {"uid": "34722233", "content": "我也想看"}, {"uid": "29678426", "content": "什么东西这么贵"}, {"uid": "29678426", "content": "你确实250、"}, {"uid": "11739836", "content": "牛"}, {"uid": "19990666", "content": "好哈人阿"}, {"uid": "34722233", "content": "草"}, {"uid": "34722233", "content": "？"}, {"uid": "29678426", "content": "要我拍肚子照发给她"}, {"uid": "34722233", "content": "嘶，馋你可还行"}, {"uid": "240648332", "content": "更新个显卡驱动他把电脑给我重启了"}, {"uid": "19990666", "content": "昨天吃的麻酱凉皮"}, {"uid": "11739836", "content": "hhh"}, {"uid": "29678426", "content": "隔壁一天天的馋我肚子，我好苦啊"}, {"uid": "34722233", "content": "旺财我的旺财"}, {"uid": "29678426", "content": "残影我的残影"}, {"uid": "9822386", "content": "吃海鲜"}, {"uid": "34722233", "content": "虾仁"}, {"uid": "11739836", "content": "喷射战士"}, {"uid": "9822386", "content": "那就别吃了"}, {"uid": "34722233", "content": "我吃的混沌"}, {"uid": "19990666", "content": "吃的炸鸡"}, {"uid": "2588719", "content": "我吃的是火锅鸭"}, {"uid": "9822386", "content": "没有人比我更懂跳脸"}, {"uid": "34722233", "content": "草"}, {"uid": "34722233", "content": "你跳脸的次数还不够多？"}, {"uid": "19990666", "content": "坏女人干啥了"}, {"uid": "9822386", "content": "给，都可以给"}, {"uid": "34722233", "content": "N久以前"}, {"uid": "34722233", "content": "我靠你还说你不会跳脸"}, {"uid": "34722233", "content": "兄弟们你们说我做的对嘛？"}, {"uid": "9822386", "content": "可别给残影气出个好歹来"}, {"uid": "240648332", "content": "帅吧 绝版了"}, {"uid": "34722233", "content": "我想给她一拳"}, {"uid": "240648332", "content": "hhhhhh"}, {"uid": "2588719", "content": "残影，这你能忍吗"}, {"uid": "2588719", "content": "还跳脸了呢"}, {"uid": "34722233", "content": "草"}, {"uid": "34722233", "content": "球球了"}, {"uid": "34722233", "content": "所以我求他复刻"}, {"uid": "34722233", "content": "看了"}, {"uid": "9822386", "content": "那你还充钱？"}, {"uid": "34722233", "content": "我真的球球了"}, {"uid": "2588719", "content": "坏女人"}, {"uid": "34722233", "content": "我求他复刻"}, {"uid": "2588719", "content": "自己恰独食是吧"}, {"uid": "34722233", "content": "！！！！！！"}, {"uid": "34722233", "content": "草"}, {"uid": "34722233", "content": "渐变啊"}, {"uid": "34722233", "content": "渐变"}, {"uid": "29678426", "content": "西巴"}, {"uid": "34722233", "content": "那个衣服绝版了"}, {"uid": "29678426", "content": "我晕"}, {"uid": "34722233", "content": "灰常感谢最后の单推赠送的24个小心心"}, {"uid": "29678426", "content": "怎么玩摩尔还充钱"}, {"uid": "2588719", "content": "让兄弟不冲，自己悄悄的冲是吧"}, {"uid": "9822386", "content": "白嫖是吧"}, {"uid": "34722233", "content": "烦死了"}, {"uid": "34722233", "content": "晚安晚安"}, {"uid": "8742831", "content": "睡了"}, {"uid": "2588719", "content": "好狠"}, {"uid": "240648332", "content": "然后自己冲了"}, {"uid": "34722233", "content": "捏嘛的"}, {"uid": "2588719", "content": "残影上当了？"}, {"uid": "29678426", "content": "多来点（"}, {"uid": "34722233", "content": "我不玩了"}, {"uid": "29678426", "content": "能不能别这么幼稚，不就是级吧吗"}, {"uid": "34722233", "content": "垃圾游戏"}, {"uid": "34722233", "content": "草"}, {"uid": "34722233", "content": "我崩溃了"}, {"uid": "34722233", "content": "撒豆天、d "}, {"uid": "240648332", "content": "好家伙"}, {"uid": "34722233", "content": "？》？！！！！！！！！"}, {"uid": "34722233", "content": "你的衣服呢？"}, {"uid": "34722233", "content": "？？？？？？？"}, {"uid": "34722233", "content": "？"}, {"uid": "174006748", "content": "游戏等什么？"}, {"uid": "34722233", "content": "旺财你还年轻"}, {"uid": "29678426", "content": "那没事了"}, {"uid": "34722233", "content": "对啊，游戏等级"}, {"uid": "29678426", "content": "以为问我"}, {"uid": "29678426", "content": "哦"}, {"uid": "2588719", "content": "怎么叫都不会醒的"}, {"uid": "29678426", "content": "我？"}, {"uid": "2588719", "content": "我之前试过，晕过去睡得比较死"}, {"uid": "2588719", "content": "那是因为你是晕过去了"}, {"uid": "34722233", "content": "28了没28了没"}, {"uid": "14794340", "content": "是因为秃头所以冷妈"}, {"uid": "14794340", "content": "这就是冷子哥吗"}, {"uid": "170228481", "content": "冷子哥不虚拟，她是电饭煲，吹风机，电暖炉"}, {"uid": "14794340", "content": "好狠"}, {"uid": "9822386", "content": "你不是四点半才睡吗"}, {"uid": "2588719", "content": "好狠"}, {"uid": "2588719", "content": "才睡了几个小时"}, {"uid": "34722233", "content": "太忙了"}, {"uid": "29678426", "content": "吃贵点，我报销"}, {"uid": "9822386", "content": "VTB都是虚拟的，旺财你把握不住"}, {"uid": "2588719", "content": "你昨天不是肝了一天了吗"}, {"uid": "29678426", "content": "_(:3」∠)_"}, {"uid": "29678426", "content": "残影真懂我心"}, {"uid": "170228481", "content": "小坏坏"}, {"uid": "14794340", "content": "冷子哥打我一拳"}, {"uid": "9822386", "content": "无内鬼，来点坏话"}, {"uid": "170228481", "content": "我爱冷冷，冷冷（）我"}, {"uid": "29678426", "content": "那不是嘛"}, {"uid": "9822386", "content": "坏话都不会说，你还饿馍呢？"}, {"uid": "34722233", "content": "草"}, {"uid": "34722233", "content": "= ="}, {"uid": "29678426", "content": "就是每个月都会来的那一天"}, {"uid": "29678426", "content": "她说月常"}, {"uid": "240648332", "content": "猫一会儿睡觉"}, {"uid": "29678426", "content": "那确实"}, {"uid": "9822386", "content": "没听清就算了，反正不是什么好话"}, {"uid": "29678426", "content": "哦"}, {"uid": "29678426", "content": "我是啥?没听清"}, {"uid": "14794340", "content": "不送了"}, {"uid": "9822386", "content": "提督又续一个月是吧"}, {"uid": "34722233", "content": "灰常感谢不服输的花长生赠送的1个小心心"}, {"uid": "9822386", "content": "旺财又在野性打钱？"}, {"uid": "34722233", "content": "灰常感谢不服输的花长生赠送的4个小心心"}, {"uid": "34722233", "content": "灰常感谢不服输的花长生赠送的7个小心心"}, {"uid": "29678426", "content": "草了"}, {"uid": "9822386", "content": "冷子哥在干什么"}, {"uid": "29678426", "content": "点进30401，情不自禁的按了续费"}, {"uid": "14794340", "content": "买了个高达"}, {"uid": "34722233", "content": "灰常感谢TokisakiKurumi1_赠送的3个小心心"}, {"uid": "14794340", "content": "（大悲）"}, {"uid": "29678426", "content": "（悲"}, {"uid": "14794340", "content": "少了一千块"}, {"uid": "29678426", "content": "我的钱也没了"}, {"uid": "14794340", "content": "我的钱没了"}, {"uid": "11739836", "content": "我听到了给他爱"}, {"uid": "14794340", "content": "草"}, {"uid": "29678426", "content": "咋了"}, {"uid": "34722233", "content": "草"}, {"uid": "29678426", "content": "男的我又残影就够了"}, {"uid": "34722233", "content": "旺财"}, {"uid": "29678426", "content": "那没事了"}, {"uid": "29678426", "content": "新妹妹？"}, {"uid": "29678426", "content": "咕噜喵是嘛呀"}, {"uid": "174006748", "content": "探头"}, {"uid": "34722233", "content": "直播间是10401"}, {"uid": "34722233", "content": "咕噜猫明天首播"}, {"uid": "34722233", "content": "对了"}, {"uid": "34722233", "content": "啊"}, {"uid": "34722233", "content": "30401yyds"}, {"uid": "34722233", "content": "确实确实"}, {"uid": "29678426", "content": "好欸，是我最最喜欢的30401"}, {"uid": "29678426", "content": "给我唱晕"}, {"uid": "29678426", "content": "唱歌"}, {"uid": "29678426", "content": "还有那种直接开腔的，简直了"}, {"uid": "29678426", "content": "是很下饭"}, {"uid": "29678426", "content": "都没有有趣的"}, {"uid": "29678426", "content": "都是阿猪阿狗"}, {"uid": "29678426", "content": "点不下手啊"}, {"uid": "29678426", "content": "继续逛陪玩(〜￣△￣)〜"}, {"uid": "11739836", "content": "我还记得二小姐鬼畜"}, {"uid": "1767437", "content": "咕噜咕噜"}, {"uid": "11739836", "content": "车万的年代我经历过，不过已经末期了"}, {"uid": "1767437", "content": "（￣3￣）♡"}, {"uid": "11739836", "content": "这歌有点久了吧"}, {"uid": "170228481", "content": "冷冷不是妹妹，冷冷是我蝶"}, {"uid": "34722233", "content": "谢谢三年A班学姐Samira的关注，谢谢"}, {"uid": "11739836", "content": "卧槽"}, {"uid": "46278110", "content": "我来看妹妹睡觉"}, {"uid": "46278110", "content": "……"}, {"uid": "29678426", "content": "太对了哥"}, {"uid": "29678426", "content": "阿西吧"}, {"uid": "170228481", "content": "那个叫学姐的pa去睡觉"}, {"uid": "29678426", "content": "点歌 avid"}, {"uid": "11739836", "content": "你看上面的点歌"}, {"uid": "34722233", "content": "灰常感谢Dota_DD赠送的1个吃瓜"}, {"uid": "11739836", "content": "秋天不回来没被pb了吧"}, {"uid": "34722233", "content": "灰常感谢筱筱墨笙赠送的7个小心心"}, {"uid": "24388845", "content": "点歌 28850500"}, {"uid": "34722233", "content": "灰常感谢小冷家的女仆狗赠送的48个小心心"}, {"uid": "170228481", "content": "点歌 秋day不回来"}, {"uid": "24388845", "content": "哈哈哈哈"}, {"uid": "24388845", "content": "而蝙蝠是倒着睡的"}, {"uid": "170228481", "content": "旺财我的旺财"}, {"uid": "29678426", "content": "你们有问题"}, {"uid": "24388845", "content": "马也是站着睡的"}, {"uid": "24388845", "content": "老板身体健康"}, {"uid": "34722233", "content": "旺财叔叔牛蛙"}, {"uid": "24388845", "content": "老板大气"}, {"uid": "24388845", "content": "感谢老板"}, {"uid": "24388845", "content": "我突然就给自己加设定了"}, {"uid": "34722233", "content": "灰常感谢小冷家的女仆狗赠送的1个提督"}, {"uid": "24388845", "content": "牛蛙"}, {"uid": "7507380", "content": "点歌 30401"}, {"uid": "34722233", "content": "搜嘎"}, {"uid": "34722233", "content": "哦"}, {"uid": "34722233", "content": "欧尼"}, {"uid": "24388845", "content": "马不是站着睡觉的吗"}, {"uid": "170228481", "content": "可以"}, {"uid": "24388845", "content": "草"}, {"uid": "24388845", "content": "倒也符合我的设定"}, {"uid": "24388845", "content": "站着睡觉是吧"}, {"uid": "34722233", "content": "站着睡"}, {"uid": "24388845", "content": "果然躺下就不困了"}, {"uid": "24388845", "content": "确实"}, {"uid": "11393528", "content": "太怪了，但在这个群到也还算合理"}, {"uid": "34722233", "content": "不愧是大土土"}, {"uid": "170228481", "content": "我发在群里的"}, {"uid": "34722233", "content": "阿七晚安"}, {"uid": "170228481", "content": "冷冷能不能读读"}, {"uid": "11331498", "content": "天亮我再来！天亮再见！冷挥挥！"}, {"uid": "34722233", "content": "草"}, {"uid": "34722233", "content": "你开游戏了？"}, {"uid": "34722233", "content": "/"}, {"uid": "14944083", "content": "你寄八谁啊哈哈哈哈"}, {"uid": "14944083", "content": "我刚刚在后台就听到一句"}, {"uid": "34722233", "content": "确实好久不见了"}, {"uid": "11331498", "content": "╮(￣▽￣)╭"}, {"uid": "11331498", "content": "好久不见甚是想念"}, {"uid": "11331498", "content": "╮(￣▽￣)╭晚上好"}, {"uid": "34722233", "content": "阿七晚好"}, {"uid": "170228481", "content": "欢迎来到摩尔庄园冷冷"}, {"uid": "34722233", "content": "帽子哥晚安"}, {"uid": "179301419", "content": "晚安"}, {"uid": "34722233", "content": "灰常感谢威厳满满の蕾米莉亚赠送的24个小心心"}, {"uid": "34722233", "content": "草"}, {"uid": "24388845", "content": "冷冷看群"}, {"uid": "11393528", "content": "老婆系（幻听）"}, {"uid": "14944083", "content": "耳朵皮看起来是憨憨的圆脸妹"}, {"uid": "34722233", "content": "明明是奶奶的感觉"}, {"uid": "34722233", "content": "屁"}, {"uid": "34722233", "content": "皮"}, {"uid": "14944083", "content": "冷冷你的旧皮有点那种大姐姐的感觉"}, {"uid": "34722233", "content": "XD"}, {"uid": "34722233", "content": "我反正都喜欢"}, {"uid": "24388845", "content": "整个人就燃えている"}, {"uid": "14944083", "content": "我发现了"}, {"uid": "24388845", "content": "好汀！"}, {"uid": "34722233", "content": "太经典了"}, {"uid": "34722233", "content": "捏嘛的"}, {"uid": "34722233", "content": "就是想不起来"}, {"uid": "34722233", "content": "我是说"}, {"uid": "34722233", "content": "是这个！"}, {"uid": "34722233", "content": "啊"}, {"uid": "11393528", "content": "有这事？"}, {"uid": "34722233", "content": "我就可以做好饭了"}, {"uid": "7507380", "content": "原来是耳朵没了（）"}, {"uid": "7507380", "content": "为什么变秃了"}, {"uid": "34722233", "content": "什么时候他说我可以嫁人了"}, {"uid": "34722233", "content": "带我拿阿憨做实验"}, {"uid": "7507380", "content": "残影牛肉"}, {"uid": "14944083", "content": "能把冷冷做成菜吗"}, {"uid": "34722233", "content": "我做饭吧行"}, {"uid": "11393528", "content": "有机会把残影烧成菜吗（x"}, {"uid": "34722233", "content": "点歌 751472"}, {"uid": "11393528", "content": "有代入感，饿了"}, {"uid": "11739836", "content": "点歌 386844"}, {"uid": "379363311", "content": "懂了"}, {"uid": "14944083", "content": "冷冷牜牜"}, {"uid": "379363311", "content": "妳也是瑪麗蘇小說愛好者"}, {"uid": "34722233", "content": "考完试赶紧拜他为师"}, {"uid": "34722233", "content": "我大伯好像以前是干酒店厨师出来的"}, {"uid": "2588719", "content": "我如果要找女朋友一定要做饭好吃的"}, {"uid": "24388845", "content": "建议自己做"}, {"uid": "2588719", "content": "我也想"}, {"uid": "11393528", "content": "可恶，那确实好幸福"}, {"uid": "379363311", "content": "會不會讀我名字"}, {"uid": "34722233", "content": "我来伦敦的这一周，我大妈他们做饭没有重样过"}, {"uid": "34722233", "content": "我发现我大哥大姐他们以前好幸福"}, {"uid": "34722233", "content": "灰常感谢璃瑩殤-三箭-夢喃赠送的1个小心心"}, {"uid": "11393528", "content": "牛牛残影！"}, {"uid": "34722233", "content": "回来了"}, {"uid": "34722233", "content": "飞来了"}, {"uid": "34722233", "content": "牛牛牛默笙"}, {"uid": "11393528", "content": "又牛啦！"}, {"uid": "14944083", "content": "没发出去"}, {"uid": "14944083", "content": "给您包邮呢 亲"}, {"uid": "14944083", "content": "在的 亲"}, {"uid": "14944083", "content": "为啥星期六 不一样"}, {"uid": "34722233", "content": "灰常感谢TokisakiKurumi1_赠送的5个小心心"}, {"uid": "34722233", "content": "谢谢祝爫的关注，谢谢"}, {"uid": "34722233", "content": "灰常感谢三七Wiess赠送的1个小心心"}, {"uid": "25922800", "content": "确实"}, {"uid": "14944083", "content": "对对对"}, {"uid": "24388845", "content": "点歌 809482"}, {"uid": "25922800", "content": "草"}, {"uid": "14944083", "content": "是发量稀少"}, {"uid": "14944083", "content": "不是秃"}, {"uid": "25922800", "content": "因为太聪明了，所以秃"}, {"uid": "25922800", "content": "聪明，绝顶"}, {"uid": "14944083", "content": "别人不说还好"}, {"uid": "8742831", "content": "嗨呀"}, {"uid": "14944083", "content": "哈哈哈哈哈"}, {"uid": "25922800", "content": "确实挺秃的"}, {"uid": "14944083", "content": "没有耳朵可爱"}, {"uid": "14944083", "content": "冷冷你是不是还有一个没有耳朵的形象来着"}, {"uid": "14944083", "content": "工作是不是特别忙 活多"}, {"uid": "14944083", "content": "好惨"}, {"uid": "14944083", "content": "已经在放假状态了"}, {"uid": "14944083", "content": "会"}, {"uid": "14944083", "content": "冷冷还在工作吗"}, {"uid": "34722233", "content": "谢谢夢乃夜紫_YAMU的关注，谢谢"}, {"uid": "11739836", "content": "可乐鸡翅黑色的也挺好吃的"}, {"uid": "14944083", "content": "还蛮香的"}, {"uid": "2588719", "content": "鸡翅吗"}, {"uid": "24388845", "content": "茄子"}, {"uid": "14944083", "content": "这种没有啥肉的翅膀 腌一下啥的"}, {"uid": "25922800", "content": "想吃奥尔良烤翅了"}, {"uid": "24388845", "content": "好汀"}, {"uid": "25922800", "content": "我也有点看饿了"}, {"uid": "14944083", "content": "看你的翅膀 看饿了（￣▽￣）"}, {"uid": "24388845", "content": "然后流眼泪的感觉吗"}, {"uid": "24388845", "content": "疯狂打哈气"}, {"uid": "34722233", "content": "灰常感谢三七Wiess赠送的1个小心心"}, {"uid": "24388845", "content": "你知道那种"}, {"uid": "34722233", "content": "吃饭去热"}, {"uid": "34722233", "content": "XD"}, {"uid": "34722233", "content": "阿当哥晚安晚安"}, {"uid": "24388845", "content": "估计躺下就精神了"}, {"uid": "24388845", "content": "去躺着黑听了"}, {"uid": "24388845", "content": "困死了"}, {"uid": "14944083", "content": "在床上"}, {"uid": "14944083", "content": "没有呀"}, {"uid": "25922800", "content": "上班叫劳动换取报酬，摸鱼才叫赚钱"}, {"uid": "25922800", "content": "确实"}, {"uid": "11739836", "content": "(〜￣△￣)〜"}, {"uid": "24388845", "content": "只有你摸鱼你才赚到了钱"}, {"uid": "2588719", "content": "确实"}, {"uid": "11739836", "content": "(〜￣△￣)〜"}, {"uid": "25922800", "content": "赚钱快乐呀"}, {"uid": "25922800", "content": "这样我提成高"}, {"uid": "172022760", "content": "晚安"}, {"uid": "34722233", "content": "二荦晚安"}, {"uid": "172022760", "content": "哈哈哈"}, {"uid": "172022760", "content": "晚安，睡了"}, {"uid": "25922800", "content": "确实"}, {"uid": "25922800", "content": "最近生意差，所以提早下班。"}, {"uid": "25922800", "content": "终于下班了"}, {"uid": "11739836", "content": "估计打错了"}, {"uid": "11739836", "content": "刚打就挂了"}, {"uid": "11739836", "content": "吓着我了"}, {"uid": "11739836", "content": "我亲戚突然给我个电话"}, {"uid": "2588719", "content": "晚安"}, {"uid": "34722233", "content": "镜音晚安"}, {"uid": "2588719", "content": "其实我有蛮多的"}, {"uid": "14912211", "content": "晚安"}, {"uid": "14912211", "content": "我睡啦。。。明天早上见"}, {"uid": "2588719", "content": "细说细说"}, {"uid": "2588719", "content": "你要聊这个我就不困了"}, {"uid": "34722233", "content": "给点给点"}, {"uid": "24388845", "content": "草"}, {"uid": "11739836", "content": "这就是我"}, {"uid": "11739836", "content": "对"}, {"uid": "24388845", "content": "来点不困的话题"}, {"uid": "2588719", "content": "住校还能迟到？"}, {"uid": "24388845", "content": "傻了"}, {"uid": "11739836", "content": "住校的，都天天迟到"}, {"uid": "24388845", "content": "疯狂打哈气"}, {"uid": "2588719", "content": "多睡点好"}, {"uid": "11739836", "content": "我比较嗜睡，所以在学校里"}, {"uid": "2588719", "content": "又不想玩电脑"}, {"uid": "2588719", "content": "实在找不到事情做"}, {"uid": "2588719", "content": "我今天下午睡了3小时"}, {"uid": "24388845", "content": "果然羊有这种功效吗"}, {"uid": "11739836", "content": "我睡了12个小时"}, {"uid": "24388845", "content": "就困了"}, {"uid": "24388845", "content": "就看了会羊人打枪"}, {"uid": "2588719", "content": "自制咸柠七"}, {"uid": "24388845", "content": "不知道为啥"}, {"uid": "24388845", "content": " 又困了"}, {"uid": "34722233", "content": "灰常感谢路过摸摸鱼赠送的1个心动卡"}, {"uid": "34722233", "content": "灰常感谢TokisakiKurumi1_赠送的4个小心心"}, {"uid": "2588719", "content": "我打算明天买个磨具，来制冰块"}, {"uid": "19990666", "content": "我准备买制冰器"}, {"uid": "2588719", "content": "比现象中要好"}, {"uid": "2588719", "content": "今天发现，冰箱的制冷还行"}, {"uid": "19990666", "content": "我影，派否？"}, {"uid": "174006748", "content": "点歌  群青"}, {"uid": "34722233", "content": "好嘞"}, {"uid": "34722233", "content": "嘶"}, {"uid": "174006748", "content": "打扰了"}, {"uid": "174006748", "content": "？"}, {"uid": "19990666", "content": "出现了，跨服交流"}, {"uid": "174006748", "content": "我t'm直接变身谜语人"}, {"uid": "174006748", "content": "怕个鬼"}, {"uid": "34722233", "content": "跳板果然是个好东西"}, {"uid": "34722233", "content": "憋坏了是吧"}, {"uid": "14944083", "content": "好耶"}, {"uid": "14944083", "content": "(～￣△￣)～"}, {"uid": "14944083", "content": "能看到我说话吗"}, {"uid": "14944083", "content": "冷冷"}, {"uid": "11739836", "content": "所以我说附加"}, {"uid": "19990666", "content": "确实是听音效去的"}, {"uid": "11739836", "content": "光看剧情也不行啊"}, {"uid": "11739836", "content": "画面和音乐都是附加项"}, {"uid": "19990666", "content": "今天周日阿，每天看吧"}, {"uid": "11739836", "content": "要我去电影院看基本都是看剧情"}, {"uid": "11739836", "content": "点歌 19945726"}, {"uid": "34722233", "content": "啊私影，看吧"}, {"uid": "19990666", "content": "好看吗，我记得之前就已经出盗版资源了"}, {"uid": "11739836", "content": "点歌 33911781"}, {"uid": "2588719", "content": "确实"}, {"uid": "34722233", "content": "确实"}, {"uid": "34722233", "content": "我就看我回国了它还在不在"}, {"uid": "19990666", "content": "扳机社的吗"}, {"uid": "34722233", "content": "真好，你还能看两次"}, {"uid": "34722233", "content": "普罗米亚"}, {"uid": "24388845", "content": "还很不错"}, {"uid": "19990666", "content": "你们都去看啥"}, {"uid": "24388845", "content": "23"}, {"uid": "24388845", "content": "我家楼下就是"}, {"uid": "34722233", "content": "草"}, {"uid": "24388845", "content": "多少钱"}, {"uid": "11739836", "content": "点歌 29734857"}, {"uid": "24388845", "content": "点歌 27712729"}, {"uid": "11739836", "content": "这番不咋地，歌倒是好听"}, {"uid": "19990666", "content": "牛蛙"}, {"uid": "11739836", "content": "数字就可以"}, {"uid": "11739836", "content": "对呀"}, {"uid": "19990666", "content": "美波的歌不是VIP吗，也能点上？"}, {"uid": "11739836", "content": "点歌 722932"}, {"uid": "34722233", "content": "嗷嗷"}, {"uid": "24388845", "content": "全电影院就我一个"}, {"uid": "24388845", "content": "爽啊"}, {"uid": "34722233", "content": "阿冷阿冷，咋样啊，今天看普罗米亚"}, {"uid": "24388845", "content": "哇安哇安"}, {"uid": "27792512", "content": "晚安晚安"}, {"uid": "34722233", "content": "茶盖晚安"}, {"uid": "27792512", "content": "明天见 臭ju"}, {"uid": "11739836", "content": "要被骂"}, {"uid": "11739836", "content": "完了"}, {"uid": "11739836", "content": "可是我一个星期都没咋练"}, {"uid": "11739836", "content": "早上去上架子鼓的课"}, {"uid": "27792512", "content": "把冷宝藏起来独享嘻嘻"}, {"uid": "34722233", "content": "摩卡晚好"}, {"uid": "16110916", "content": "点歌 おまじない mink"}, {"uid": "304765334", "content": "冷冷冷冷晚好"}, {"uid": "27792512", "content": "是的 3个上下铺"}, {"uid": "27792512", "content": "明天半夜再来 可不能被逮住看冷冷了"}, {"uid": "26896746", "content": "怪起来了"}, {"uid": "24388845", "content": "草"}, {"uid": "2588719", "content": "教练可还行"}, {"uid": "27792512", "content": "是的"}, {"uid": "2588719", "content": "对的"}, {"uid": "27792512", "content": "我上次去的6人房"}, {"uid": "2588719", "content": "弄六张又太浪费了"}, {"uid": "24388845", "content": "我不能玩守望先锋吗"}, {"uid": "26896746", "content": "之前我睡的四人间有五个人的位置"}, {"uid": "27792512", "content": "有的"}, {"uid": "16110916", "content": "可惜我去不了"}, {"uid": "2588719", "content": "因为会凸出来"}, {"uid": "34722233", "content": "不会吧，真的是辅助和AD一块睡？"}, {"uid": "24388845", "content": "有么有6人房"}, {"uid": "16110916", "content": "旅游啊。。我也好想去"}, {"uid": "2588719", "content": "我去过一次，也只有四张c"}, {"uid": "26896746", "content": "或者是中野辅一起"}, {"uid": "27792512", "content": "好像也是4.。"}, {"uid": "16110916", "content": "不妥.jpg"}, {"uid": "26896746", "content": "也有可能是中野一起"}, {"uid": "7507380", "content": "让ADC睡厕所"}, {"uid": "7507380", "content": "不可"}, {"uid": "11739836", "content": "草"}, {"uid": "34722233", "content": "草"}, {"uid": "2588719", "content": "草"}, {"uid": "27792512", "content": "我在杭州边边上 去城里和朋友"}, {"uid": "34722233", "content": "嘶"}, {"uid": "26896746", "content": "♡电♡竞♡酒♡店♡"}, {"uid": "2588719", "content": "电/竞酒店蛮便宜的"}, {"uid": "27792512", "content": "我打了好几次"}, {"uid": "27792512", "content": "打不出来"}, {"uid": "16110916", "content": "粉丝团名字换了？"}, {"uid": "27792512", "content": "酒店"}, {"uid": "26896746", "content": "明天要去一楼洗衣服"}, {"uid": "27792512", "content": "竞"}, {"uid": "27792512", "content": "电"}, {"uid": "27792512", "content": "去"}, {"uid": "27792512", "content": "明天要去杭州"}, {"uid": "26896746", "content": "再睡了再睡了"}, {"uid": "27792512", "content": "晚安 juju"}, {"uid": "26896746", "content": "这样才能吸引别人买票"}, {"uid": "26896746", "content": "断的好哇"}, {"uid": "24388845", "content": "确实"}, {"uid": "26896746", "content": "点歌 反转地球"}, {"uid": "3641918", "content": "断的我想当场给你一大嘴巴子"}, {"uid": "26896746", "content": "我预判了你的预判"}, {"uid": "3641918", "content": "断的好啊"}, {"uid": "26896746", "content": "诶"}, {"uid": "3388335", "content": "卧槽"}, {"uid": "24388845", "content": "这个位置还不错"}, {"uid": "26896746", "content": "点歌 晚安喵"}, {"uid": "3388335", "content": "有断章狗"}, {"uid": "24388845", "content": "确实"}, {"uid": "26896746", "content": "突然就不难了"}, {"uid": "7507380", "content": "?"}, {"uid": "26896746", "content": "听到晚安喵也太难了"}, {"uid": "26896746", "content": "呜呜呜"}, {"uid": "24388845", "content": "确实是一个细节"}, {"uid": "24388845", "content": "不当谜语人怎么让狼自爆啊"}, {"uid": "34722233", "content": "灰常感谢奎21赠送的48个小心心"}, {"uid": "26896746", "content": "冷宝今天好可爱"}, {"uid": "2588719", "content": "就是要主角这个工具人说"}, {"uid": "170228481", "content": "冷冷，什么时候2000粉纪念，很急"}, {"uid": "24388845", "content": "牛蛙"}, {"uid": "26896746", "content": "不过是换个地方看冷宝罢了"}, {"uid": "26896746", "content": "高考"}, {"uid": "34722233", "content": "加油吧反正"}, {"uid": "34722233", "content": "深圳的话是挺难的"}, {"uid": "24388845", "content": "加油"}, {"uid": "294955251", "content": "深圳学生好难啊"}, {"uid": "24388845", "content": "雾切直接一个陷阱的放"}, {"uid": "26896746", "content": "要高考了怎么办哇"}, {"uid": "34722233", "content": "你们紧张的嘚"}, {"uid": "34722233", "content": "我都没紧张"}, {"uid": "34722233", "content": "不是，我才是那个高三的"}, {"uid": "26896746", "content": "呜呜呜"}, {"uid": "34722233", "content": "我记得老爷爷之前说过"}, {"uid": "26896746", "content": "我好紧张哇"}, {"uid": "34722233", "content": "我信"}, {"uid": "26896746", "content": "明天就高考了"}, {"uid": "34722233", "content": "啊"}, {"uid": "26896746", "content": "就是就是"}, {"uid": "34722233", "content": "那你有啥紧张的"}, {"uid": "294955251", "content": "但是也不一定"}, {"uid": "294955251", "content": "我不要啊"}, {"uid": "294955251", "content": "我好紧张"}, {"uid": "294955251", "content": "我"}, {"uid": "34722233", "content": "灰常感谢鋼鐵加魯魯Garurumon赠送的1个这个好诶"}, {"uid": "241774213", "content": "14了"}, {"uid": "34722233", "content": "灰常感谢单推人kurumi赠送的1个小心心"}, {"uid": "24388845", "content": "确实"}, {"uid": "34722233", "content": "灰常感谢单推人kurumi赠送的9个小心心"}, {"uid": "24388845", "content": "这样你也不热了233"}, {"uid": "26896746", "content": "我怕被子中暑哇"}, {"uid": "26896746", "content": "- -"}, {"uid": "241774213", "content": "晚上好"}, {"uid": "24388845", "content": "别让被子着凉了"}, {"uid": "26896746", "content": "我不好了哇"}, {"uid": "24388845", "content": "那被子盖你"}, {"uid": "34722233", "content": "嘻嘻被你发现惹"}, {"uid": "26896746", "content": "盖被子好热"}, {"uid": "24388845", "content": "？"}, {"uid": "34722233", "content": "XD"}, {"uid": "34722233", "content": "我不管，阿当哥你就得给我晚安"}, {"uid": "24388845", "content": "晚安"}, {"uid": "26896746", "content": "安安安安娜娜安安安安"}, {"uid": "34722233", "content": "阿当哥晚安"}, {"uid": "174006748", "content": "残影晚上好"}, {"uid": "24388845", "content": "无情的晚安机器"}, {"uid": "34722233", "content": "揽月晚安"}, {"uid": "26896746", "content": "我会想你的呜呜呜"}, {"uid": "26896746", "content": "宝多喝水"}, {"uid": "34722233", "content": "一字晚好"}, {"uid": "2588719", "content": "这不是老板铁锅吗"}, {"uid": "4519779", "content": "好骂"}, {"uid": "24388845", "content": "给他一拳"}, {"uid": "3641918", "content": "我7点半的早班"}, {"uid": "3641918", "content": "兄弟们6点半吵醒我"}, {"uid": "34722233", "content": "琴音晚安"}, {"uid": "34722233", "content": "琴音晚好"}, {"uid": "41330105", "content": "安"}, {"uid": "24388845", "content": "这个结束就保存吧"}, {"uid": "4519779", "content": "_(:3」∠)_"}, {"uid": "4519779", "content": "好耶"}, {"uid": "24388845", "content": "是的"}, {"uid": "24388845", "content": "233"}, {"uid": "24388845", "content": "这种游戏我血压就没问题"}, {"uid": "26896746", "content": "（￣▽￣）"}, {"uid": "34722233", "content": "是"}, {"uid": "4519779", "content": "今天是不是超能力女儿鸭"}, {"uid": "34722233", "content": "朱哥晚安"}, {"uid": "3641918", "content": "睡觉去"}, {"uid": "3641918", "content": "血压高"}, {"uid": "3641918", "content": "不看了"}, {"uid": "24388845", "content": "上班咯"}, {"uid": "2588719", "content": "现在一点了"}, {"uid": "24388845", "content": "就是菜单里言弹后面的介绍"}, {"uid": "24388845", "content": "你可以看下言弹的详细"}, {"uid": "24388845", "content": "老婆都提示你了"}, {"uid": "24388845", "content": "慢慢想"}, {"uid": "4519779", "content": "我出狱了"}, {"uid": "34722233", "content": "对"}, {"uid": "4519779", "content": "诶 能发弹幕了"}, {"uid": "24388845", "content": "你这打的合理吗"}, {"uid": "34722233", "content": "阿尘晚好"}, {"uid": "24388845", "content": "很关键"}, {"uid": "24388845", "content": "这里不要说"}, {"uid": "24388845", "content": "注意不要发有剧透性的弹幕哦"}, {"uid": "24388845", "content": "牛蛙"}, {"uid": "29678426", "content": "解封了，欸爽"}, {"uid": "2588719", "content": "谜语人给你马来一拳"}, {"uid": "2588719", "content": "这些b自己都知道，就是不说"}, {"uid": "34722233", "content": "旺财晚好"}, {"uid": "34722233", "content": "花甲晚好"}, {"uid": "3388335", "content": "嗯猜"}, {"uid": "24388845", "content": "认真看啊"}, {"uid": "3388335", "content": "有人在"}, {"uid": "24388845", "content": "哒呗"}, {"uid": "24388845", "content": "不知道"}, {"uid": "26896746", "content": "化身花露水战士"}, {"uid": "26896746", "content": "我直接进行一个花露水的喷"}, {"uid": "34722233", "content": "这游戏老长了"}, {"uid": "2588719", "content": "行不通"}, {"uid": "38134407", "content": "这游戏还没通关啊"}, {"uid": "38134407", "content": "晚好残影"}, {"uid": "2588719", "content": "所以需要一个女的门卡开门"}, {"uid": "34722233", "content": "黑鳄晚好"}, {"uid": "2588719", "content": "因为死者是男的，但是尸体在女更衣室发现"}, {"uid": "38134407", "content": "啊 晚上好"}, {"uid": "24388845", "content": "注意不要发有剧透性的弹幕哦"}, {"uid": "34722233", "content": "灰常感谢失忆的葑纆赠送的15个小心心"}, {"uid": "34722233", "content": "灰常感谢失忆的葑纆赠送的13个小心心"}, {"uid": "27792512", "content": "干什么干什么"}, {"uid": "2588719", "content": "的"}, {"uid": "2588719", "content": "所以凶手一定是个女耳朵"}, {"uid": "27792512", "content": "不客气"}, {"uid": "24388845", "content": "因为冷冷是女的应该可以察觉吧"}, {"uid": "34722233", "content": "灰常感谢贤者修自也赠送的8个小心心"}, {"uid": "2588719", "content": "不这样怎么显示主角牛*呢"}, {"uid": "24388845", "content": "游戏为了烟雾弹刻意把不二咲的名字放在最后"}, {"uid": "24388845", "content": "是"}, {"uid": "24388845", "content": "全都就凭看的猜出来了"}, {"uid": "2588719", "content": "确实，这个不是很明显的吗"}, {"uid": "24388845", "content": "第二章埋的两个坑"}, {"uid": "27792512", "content": "我给你一拳 臭ju"}, {"uid": "24388845", "content": "冷冷的洞察力真的牛"}, {"uid": "34722233", "content": "好耶"}, {"uid": "24388845", "content": "老婆救我"}, {"uid": "34722233", "content": "老婆来了"}, {"uid": "24388845", "content": "快进塞妹的声音好听"}, {"uid": "24388845", "content": "注意不要发有剧透性的弹幕哦"}, {"uid": "24388845", "content": "吵架不如音游"}, {"uid": "24388845", "content": "才会玩音游"}, {"uid": "15349989", "content": "_(:3」∠)_"}, {"uid": "24388845", "content": "不一定是凶手"}, {"uid": "24388845", "content": "我只能告诉你"}, {"uid": "470330", "content": "_(:3」∠)_"}, {"uid": "24388845", "content": "他急了"}, {"uid": "24388845", "content": "这个能蒙到"}, {"uid": "2588719", "content": "好蒙"}, {"uid": "3388335", "content": "不用看都能玩是吧"}, {"uid": "24388845", "content": "是冷尔摩斯"}, {"uid": "3388335", "content": "福尔摩斯"}, {"uid": "3388335", "content": "草"}, {"uid": "24388845", "content": "注意不要发有剧透性的弹幕哦"}, {"uid": "3388335", "content": "现场"}, {"uid": "24388845", "content": "兄弟萌有3级头"}, {"uid": "2588719", "content": "笑死"}, {"uid": "3641918", "content": "你就是马枪王？？"}, {"uid": "3388335", "content": "好美的中国话"}, {"uid": "2588719", "content": "哈哈哈"}, {"uid": "2588719", "content": "打空了，草"}, {"uid": "24388845", "content": "哈哈哈哈哈哈哈哈哈哈"}, {"uid": "3641918", "content": "直接打台灯"}, {"uid": "405342305", "content": "好耶"}, {"uid": "24388845", "content": "这个系统还好"}, {"uid": "2588719", "content": "当时没有说被害人是谁，他怎么知道是女的"}, {"uid": "24388845", "content": "我记错了"}, {"uid": "24388845", "content": "XD"}, {"uid": "24388845", "content": "左键"}, {"uid": "24388845", "content": "注意不要发有剧透性的弹幕哦注意不要发有剧透性的弹幕哦左键"}, {"uid": "2588719", "content": "左键长按吧"}, {"uid": "24388845", "content": "右键长摁"}, {"uid": "3641918", "content": "不二咲"}, {"uid": "2588719", "content": "按住鼠标左键"}, {"uid": "24388845", "content": "我会错意了"}, {"uid": "24388845", "content": "你的意思"}, {"uid": "24388845", "content": "懂了"}, {"uid": "24388845", "content": "233"}, {"uid": "2588719", "content": "？"}, {"uid": "24388845", "content": "你是不是也不知道冷冷是女的"}, {"uid": "2588719", "content": "他怎么知道被害人是女的？"}, {"uid": "2588719", "content": "首先排除十神的嫌疑"}, {"uid": "24388845", "content": "注意不要发有剧透性的弹幕哦"}, {"uid": "2588719", "content": "这波叫做明踩暗洗"}, {"uid": "24388845", "content": "翔姐武力值仅次于大神"}, {"uid": "2588719", "content": "说多错多"}, {"uid": "2588719", "content": "这种我觉得不说话最好"}, {"uid": "24388845", "content": "又不是另一个人格"}, {"uid": "24388845", "content": "腐川会讨厌剪刀吧"}, {"uid": "2588719", "content": "我觉得可以试试"}, {"uid": "24388845", "content": "不过3代还真加了那样的玩法"}, {"uid": "24388845", "content": "一起七嘴八舌观感不好吧"}, {"uid": "2588719", "content": "其他全是在划水的"}, {"uid": "24388845", "content": "牛蛙"}, {"uid": "11393528", "content": "我好感动"}, {"uid": "2588719", "content": "冰箱冻的还是蛮好用的"}, {"uid": "11393528", "content": "可以顺畅的发弹幕了呜呜呜"}, {"uid": "34722233", "content": "默笙晚牛牛"}, {"uid": "34722233", "content": "摩卡晚好"}, {"uid": "11393528", "content": "牛牛冷冷牛牛残影！！"}, {"uid": "11739836", "content": "vivy更新啦我要去看vv"}, {"uid": "24388845", "content": "闲的没事也可以用右键在屏幕上打节奏233"}, {"uid": "24388845", "content": "翔姐的声优真的牛"}, {"uid": "24388845", "content": "为什么不冲"}, {"uid": "24388845", "content": "翔姐还是挺萌的"}, {"uid": "34722233", "content": "想了想算了"}, {"uid": "34722233", "content": "有点大胆点想法"}, {"uid": "24388845", "content": "这就是爱吧"}, {"uid": "26896746", "content": "牛蛙"}, {"uid": "24388845", "content": "不同字血不同"}, {"uid": "24388845", "content": "有血量的"}, {"uid": "24388845", "content": "多点几下"}, {"uid": "24388845", "content": "注意不要发有剧透性的弹幕哦"}, {"uid": "34722233", "content": "灰常感谢奎21赠送的1个吃瓜"}, {"uid": "34722233", "content": "这么说的话那个剪刀不是重点"}, {"uid": "170228481", "content": "冷冷冷冷冷冷冷冷冷冷"}, {"uid": "24388845", "content": "你言弹打到错误的黄色弹幕才会错误"}, {"uid": "26896746", "content": "饿馍的cpu只能处理一件事情"}, {"uid": "24388845", "content": "你点错了它也不减分的233"}, {"uid": "26896746", "content": "就是就是"}, {"uid": "24388845", "content": "消音弹没有时间"}, {"uid": "24388845", "content": "会加分的"}, {"uid": "26896746", "content": "呜呜呜"}, {"uid": "24388845", "content": "直接摁就行了"}, {"uid": "24388845", "content": "右键打"}, {"uid": "24388845", "content": "粉色的"}, {"uid": "26896746", "content": "难道后悔没设置成亲切嘛"}, {"uid": "24388845", "content": "打了会加时间"}, {"uid": "24388845", "content": "对"}, {"uid": "26896746", "content": "哪路或多"}, {"uid": "24388845", "content": "我不说是谁hhhh"}, {"uid": "24388845", "content": "这都打不中"}, {"uid": "26896746", "content": "少有的看冷宝打不准"}, {"uid": "26896746", "content": "好"}, {"uid": "24388845", "content": "xdm有夕阳红"}, {"uid": "24388845", "content": "那个是扎在头上的吧"}, {"uid": "26896746", "content": "啥哇"}, {"uid": "24388845", "content": "sp不够是吧"}, {"uid": "24388845", "content": "弹丸的老传统了"}, {"uid": "24388845", "content": "每章的装修都不一样"}, {"uid": "24388845", "content": "主人罢了"}, {"uid": "9822386", "content": "去别处有机会的话给冷子哥进行一个流的引"}, {"uid": "9822386", "content": "直接去进行一个市场的调研"}, {"uid": "24388845", "content": "偷菜给你一拳（"}, {"uid": "9822386", "content": "给冷子哥打个招呼"}, {"uid": "26896746", "content": "去偷冷宝的菜"}, {"uid": "26896746", "content": "揪咪"}, {"uid": "34722233", "content": "这个都暗示了"}, {"uid": "24388845", "content": "第一章都2个小时"}, {"uid": "24388845", "content": "感觉审判时间不够"}, {"uid": "24388845", "content": "去拿个冰淇淋"}, {"uid": "24388845", "content": "不要发有剧透性的弹幕哦"}, {"uid": "24388845", "content": "就好像偷菜一样"}, {"uid": "24388845", "content": "有这种设定也太怪了吧"}, {"uid": "24388845", "content": "那你怎么进出自如的"}, {"uid": "24388845", "content": "草"}, {"uid": "34722233", "content": "有可能"}, {"uid": "24388845", "content": "门上"}, {"uid": "24388845", "content": "上面还写着名字呢"}, {"uid": "24388845", "content": "雾切"}, {"uid": "24388845", "content": "换门也太蠢了"}, {"uid": "34722233", "content": "阿当哥晚好啊"}, {"uid": "24388845", "content": "不要发有剧透性的弹幕哦"}, {"uid": "3641918", "content": "？？"}, {"uid": "24388845", "content": "晚上好"}, {"uid": "34722233", "content": "朱哥晚好"}, {"uid": "7507380", "content": "唥唥偶啲唥唥"}, {"uid": "34722233", "content": "嘿妹妹"}, {"uid": "34722233", "content": "看吧"}, {"uid": "34722233", "content": "不是，你说的有道理啊"}, {"uid": "34722233", "content": "啊"}, {"uid": "34722233", "content": "刀了刀了"}, {"uid": "34722233", "content": "牛蛙"}, {"uid": "34722233", "content": "我曹"}, {"uid": "34722233", "content": "没了？"}, {"uid": "6754927", "content": "噢糊"}, {"uid": "26896746", "content": "我直接进行一个火星的文"}, {"uid": "6754927", "content": "冷死哥我的冷子哥"}, {"uid": "26896746", "content": "我能打晚安了"}, {"uid": "26896746", "content": "就是就是"}, {"uid": "6754927", "content": "晚好呀残影"}, {"uid": "34722233", "content": "太不易了"}, {"uid": "34722233", "content": "确实"}, {"uid": "6754927", "content": "我的妈耶 终于解封了。"}, {"uid": "7507380", "content": "你问残影"}, {"uid": "34722233", "content": "嗯"}, {"uid": "226258108", "content": "新加坡？"}, {"uid": "6754927", "content": "噢噢噢噢噢噢噢"}, {"uid": "34722233", "content": "小Z晚好啊"}, {"uid": "7507380", "content": "我拿个东西"}, {"uid": "7507380", "content": "开黑啦等我一下"}, {"uid": "7507380", "content": "可以"}, {"uid": "226258108", "content": "我也来"}, {"uid": "34722233", "content": "来当海贼王吧"}, {"uid": "34722233", "content": "咕噜噜"}, {"uid": "7507380", "content": "这还没冷子哥大"}, {"uid": "34722233", "content": "太对了"}, {"uid": "34722233", "content": "噗"}, {"uid": "34722233", "content": "搞神秘是吧"}, {"uid": "34722233", "content": "怎么一个二个都有事要搞"}, {"uid": "34722233", "content": "草"}, {"uid": "34722233", "content": "最后一个再去"}, {"uid": "34722233", "content": "诶就是玩"}, {"uid": "34722233", "content": "你就不去看"}, {"uid": "34722233", "content": "感觉像她"}, {"uid": "491594507", "content": "打卡"}, {"uid": "34722233", "content": "+1"}, {"uid": "26896746", "content": "我哭着求了"}, {"uid": "34722233", "content": "面面晚好"}, {"uid": "34722233", "content": "死傲娇"}, {"uid": "26896746", "content": "呜呜呜求求你了"}, {"uid": "34722233", "content": "哦，也对"}, {"uid": "34722233", "content": "有别人来的话应该会被看到吧"}, {"uid": "26896746", "content": "晚晚晚"}, {"uid": "34722233", "content": "之前他不是一直都在档案室嘛"}, {"uid": "26896746", "content": "ju宝的我"}, {"uid": "34722233", "content": "揽月晚好"}, {"uid": "26896746", "content": "宝"}, {"uid": "34722233", "content": "谢谢十色柯基赠送的1个舰长~"}, {"uid": "130037282", "content": "我好想你乌乌"}, {"uid": "130037282", "content": "妈咪我的妈咪！"}, {"uid": "34722233", "content": "天琊晚安"}, {"uid": "34722233", "content": "柯基晚好"}, {"uid": "69999", "content": "冷宝贴 我先去睡了 "}, {"uid": "2588719", "content": "残影晚上好"}, {"uid": "2588719", "content": "晚上好晚上好"}, {"uid": "34722233", "content": "葑纆晚好"}, {"uid": "34722233", "content": "zero晚好啊~"}, {"uid": "7765601", "content": "晚好 suki"}, {"uid": "7765601", "content": "冷宝！"}, {"uid": "13008587", "content": "baka不准晚安 给我看"}, {"uid": "34722233", "content": "baka晚安"}, {"uid": "1768632", "content": "睡觉"}, {"uid": "1768632", "content": "886"}, {"uid": "1768632", "content": "吧"}, {"uid": "1768632", "content": "死鬼"}, {"uid": "1768632", "content": "见面了"}, {"uid": "1768632", "content": "只能在这种鬼地方见面礼"}, {"uid": "1768632", "content": "qs"}, {"uid": "13008587", "content": "好久不见了"}, {"uid": "1768632", "content": "呜啥"}, {"uid": "1768632", "content": "呜呜呜"}, {"uid": "13008587", "content": "呜呜呜"}, {"uid": "13008587", "content": "把卡 我滴baka"}, {"uid": "13008587", "content": "baka"}, {"uid": "1768632", "content": "榜一大佬来了"}, {"uid": "34722233", "content": "谢谢谜一样的Baka赠送的1个心动卡~"}, {"uid": "34722233", "content": "baka晚好"}, {"uid": "34722233", "content": "儿子有点多"}, {"uid": "13008587", "content": "妈咪系是什么标签啊"}, {"uid": "34722233", "content": "dota 晚好"}, {"uid": "14912211", "content": "那家伙也不会"}, {"uid": "14912211", "content": "我。。。。找朋友收的二手。。。"}, {"uid": "14912211", "content": "买了两个月都还在盒子里"}, {"uid": "14912211", "content": "话说。。。声卡怎么调啊=。="}, {"uid": "34722233", "content": "（测试）"}, {"uid": "27792512", "content": "没干什么没干什么"}, {"uid": "27792512", "content": "干什么干什么"}, {"uid": "27792512", "content": "残影好"}, {"uid": "34722233", "content": "茶盖晚好"}, {"uid": "27792512", "content": "臭ju 我的臭ju"}, {"uid": "34722233", "content": "我现在没有跳板"}, {"uid": "34722233", "content": "正常了"}, {"uid": "14912211", "content": "我黑听玩会儿2333"}, {"uid": "34722233", "content": "6"}, {"uid": "34722233", "content": "4"}, {"uid": "34722233", "content": "镜音晚好"}, {"uid": "14912211", "content": "晚上好"}, {"uid": "34722233", "content": "开了"}, {"uid": "34722233", "content": "嘶"}]